[
  {
    "Type": "AnimLayersAsset",
    "Name": "DA_AnimLayers",
    "Class": "UScriptClass'AnimLayersAsset'",
    "ClassPath": "/Script/AvaAnimation.AnimLayersAsset",
    "Properties": {
      "Layers": [
        {
          "LayerName": "Base",
          "MaxLODLevel": -1,
          "BlendType": "EAnimationRequestLayerBlendType::BlendAndReplace",
          "bRecordLastSequence": true,
          "LayerMask": null
        },
        {
          "LayerName": "Additive",
          "MaxLODLevel": -1,
          "BlendType": "EAnimationRequestLayerBlendType::BlendAndAdd",
          "bRecordLastSequence": false,
          "LayerMask": null
        },
        {
          "LayerName": "Replace",
          "MaxLODLevel": -1,
          "BlendType": "EAnimationRequestLayerBlendType::BlendAndReplace",
          "bRecordLastSequence": true,
          "LayerMask": null
        },
        {
          "LayerName": "BoneMask",
          "MaxLODLevel": -1,
          "BlendType": "EAnimationRequestLayerBlendType::BlendAndReplace",
          "bRecordLastSequence": false,
          "LayerMask": null
        },
        {
          "LayerName": "Conv-Ambient",
          "MaxLODLevel": -1,
          "BlendType": "EAnimationRequestLayerBlendType::BlendAndReplace",
          "bRecordLastSequence": false,
          "LayerMask": null
        },
        {
          "LayerName": "Conv-Base",
          "MaxLODLevel": -1,
          "BlendType": "EAnimationRequestLayerBlendType::BlendAndReplace",
          "bRecordLastSequence": false,
          "LayerMask": null
        },
        {
          "LayerName": "Conv-Transition",
          "MaxLODLevel": -1,
          "BlendType": "EAnimationRequestLayerBlendType::Replacement",
          "bRecordLastSequence": false,
          "LayerMask": null
        },
        {
          "LayerName": "Conv-WeightShift (+)",
          "MaxLODLevel": -1,
          "BlendType": "EAnimationRequestLayerBlendType::Additive",
          "bRecordLastSequence": false,
          "LayerMask": null
        },
        {
          "LayerName": "Conv-Lean (+)",
          "MaxLODLevel": -1,
          "BlendType": "EAnimationRequestLayerBlendType::Additive",
          "bRecordLastSequence": false,
          "LayerMask": null
        },
        {
          "LayerName": "Conv-Shrug (+)",
          "MaxLODLevel": -1,
          "BlendType": "EAnimationRequestLayerBlendType::Additive",
          "bRecordLastSequence": false,
          "LayerMask": null
        },
        {
          "LayerName": "Conv-HandGesture (+)",
          "MaxLODLevel": -1,
          "BlendType": "EAnimationRequestLayerBlendType::Additive",
          "bRecordLastSequence": false,
          "LayerMask": null
        },
        {
          "LayerName": "Conv-Breathe (+)",
          "MaxLODLevel": -1,
          "BlendType": "EAnimationRequestLayerBlendType::Additive",
          "bRecordLastSequence": false,
          "LayerMask": null
        },
        {
          "LayerName": "Conv-IdleBreak",
          "MaxLODLevel": -1,
          "BlendType": "EAnimationRequestLayerBlendType::Replacement",
          "bRecordLastSequence": false,
          "LayerMask": null
        },
        {
          "LayerName": "Conv-HeadTilt (+)",
          "MaxLODLevel": -1,
          "BlendType": "EAnimationRequestLayerBlendType::Additive",
          "bRecordLastSequence": false,
          "LayerMask": null
        },
        {
          "LayerName": "Conv-HeadBob/Nod (+)",
          "MaxLODLevel": -1,
          "BlendType": "EAnimationRequestLayerBlendType::Additive",
          "bRecordLastSequence": false,
          "LayerMask": null
        },
        {
          "LayerName": "Conv-Fixup (+)",
          "MaxLODLevel": -1,
          "BlendType": "EAnimationRequestLayerBlendType::Additive",
          "bRecordLastSequence": false,
          "LayerMask": null
        },
        {
          "LayerName": "Cin - Replace",
          "MaxLODLevel": -1,
          "BlendType": "EAnimationRequestLayerBlendType::BlendAndReplace",
          "bRecordLastSequence": true,
          "LayerMask": null
        },
        {
          "LayerName": "Conv-Brow (+)",
          "MaxLODLevel": -1,
          "BlendType": "EAnimationRequestLayerBlendType::Additive",
          "bRecordLastSequence": false,
          "LayerMask": null
        },
        {
          "LayerName": "Conv-Eye Dart (+)",
          "MaxLODLevel": 2,
          "BlendType": "EAnimationRequestLayerBlendType::Additive",
          "bRecordLastSequence": false,
          "LayerMask": {
            "ObjectName": "AnimMaskAsset'AMSK_Biped_Layer_EyeDart'",
            "ObjectPath": "/Game/Animation/Masks/AMSK_Biped_Layer_EyeDart.0"
          }
        },
        {
          "LayerName": "Conv-Blink (+)",
          "MaxLODLevel": 2,
          "BlendType": "EAnimationRequestLayerBlendType::Additive",
          "bRecordLastSequence": false,
          "LayerMask": {
            "ObjectName": "AnimMaskAsset'AMSK_Biped_Layer_EyeDart'",
            "ObjectPath": "/Game/Animation/Masks/AMSK_Biped_Layer_EyeDart.0"
          }
        },
        {
          "LayerName": "AmbientEyes",
          "MaxLODLevel": 1,
          "BlendType": "EAnimationRequestLayerBlendType::Modify",
          "bRecordLastSequence": false,
          "LayerMask": null
        },
        {
          "LayerName": "FacialEmotion",
          "MaxLODLevel": 1,
          "BlendType": "EAnimationRequestLayerBlendType::BlendAndReplace",
          "bRecordLastSequence": false,
          "LayerMask": {
            "ObjectName": "AnimMaskAsset'AMSK_Facial_FaceOnly'",
            "ObjectPath": "/Game/Animation/Masks/Facial/AMSK_Facial_FaceOnly.0"
          }
        },
        {
          "LayerName": "PerClipFacialLayer",
          "MaxLODLevel": 1,
          "BlendType": "EAnimationRequestLayerBlendType::BlendAndReplace",
          "bRecordLastSequence": false,
          "LayerMask": {
            "ObjectName": "AnimMaskAsset'AMSK_Facial_FaceOnly'",
            "ObjectPath": "/Game/Animation/Masks/Facial/AMSK_Facial_FaceOnly.0"
          }
        },
        {
          "LayerName": "FacialAnimationByTag",
          "MaxLODLevel": 1,
          "BlendType": "EAnimationRequestLayerBlendType::BlendAndReplace",
          "bRecordLastSequence": false,
          "LayerMask": {
            "ObjectName": "AnimMaskAsset'AMSK_Facial_FaceOnly'",
            "ObjectPath": "/Game/Animation/Masks/Facial/AMSK_Facial_FaceOnly.0"
          }
        },
        {
          "LayerName": "Facial",
          "MaxLODLevel": 1,
          "BlendType": "EAnimationRequestLayerBlendType::BlendAndReplace",
          "bRecordLastSequence": false,
          "LayerMask": {
            "ObjectName": "AnimMaskAsset'AMSK_Facial_FaceOnly'",
            "ObjectPath": "/Game/Animation/Masks/Facial/AMSK_Facial_FaceOnly.0"
          }
        },
        {
          "LayerName": "DialogueMouthOnly",
          "MaxLODLevel": 1,
          "BlendType": "EAnimationRequestLayerBlendType::BlendAndReplace",
          "bRecordLastSequence": false,
          "LayerMask": {
            "ObjectName": "AnimMaskAsset'AMSK_Facial_MouthOn'",
            "ObjectPath": "/Game/Animation/Masks/Facial/AMSK_Facial_MouthOn.0"
          }
        },
        {
          "LayerName": "DialogueFaceOnly",
          "MaxLODLevel": 1,
          "BlendType": "EAnimationRequestLayerBlendType::BlendAndReplace",
          "bRecordLastSequence": false,
          "LayerMask": {
            "ObjectName": "AnimMaskAsset'AMSK_Facial_FaceOnly'",
            "ObjectPath": "/Game/Animation/Masks/Facial/AMSK_Facial_FaceOnly.0"
          }
        },
        {
          "LayerName": "DialogueHeadOnly",
          "MaxLODLevel": 1,
          "BlendType": "EAnimationRequestLayerBlendType::BlendAndAdd",
          "bRecordLastSequence": false,
          "LayerMask": {
            "ObjectName": "AnimMaskAsset'AMSK_Facial_HeadBoneOnly'",
            "ObjectPath": "/Game/Animation/Masks/Facial/AMSK_Facial_HeadBoneOnly.0"
          }
        },
        {
          "LayerName": "AimEyes",
          "MaxLODLevel": 1,
          "BlendType": "EAnimationRequestLayerBlendType::Modify",
          "bRecordLastSequence": false,
          "LayerMask": null
        },
        {
          "LayerName": "PoseBlinkNotify",
          "MaxLODLevel": 1,
          "BlendType": "EAnimationRequestLayerBlendType::Replacement",
          "bRecordLastSequence": false,
          "LayerMask": {
            "ObjectName": "AnimMaskAsset'AMSK_Facial_PoseBlinkOnly'",
            "ObjectPath": "/Game/Animation/Masks/Facial/AMSK_Facial_PoseBlinkOnly.0"
          }
        },
        {
          "LayerName": "PerfCap",
          "MaxLODLevel": -1,
          "BlendType": "EAnimationRequestLayerBlendType::Replacement",
          "bRecordLastSequence": false,
          "LayerMask": null
        },
        {
          "LayerName": "ClothPoses",
          "MaxLODLevel": -1,
          "BlendType": "EAnimationRequestLayerBlendType::Modify",
          "bRecordLastSequence": false,
          "LayerMask": null
        }
      ]
    }
  }
]