[
  {
    "Type": "BodySetup",
    "Name": "BodySetup_0",
    "Outer": "VFX_SM_Troll_Pro_Split_C",
    "Class": "UScriptClass'BodySetup'",
    "Properties": {
      "AggGeom": {
        "ConvexElems": [
          {
            "VertexData": [
              {
                "X": 34.646297,
                "Y": 5.103696,
                "Z": 5.771302
              },
              {
                "X": 34.646297,
                "Y": -13.478711,
                "Z": 5.7713017
              },
              {
                "X": 34.646297,
                "Y": -13.478709,
                "Z": 6.2287025
              },
              {
                "X": 34.646297,
                "Y": 5.103697,
                "Z": 6.228703
              },
              {
                "X": -34.646297,
                "Y": -15.103707,
                "Z": -15.771289
              },
              {
                "X": -34.646297,
                "Y": -13.614674,
                "Z": -17.260323
              },
              {
                "X": -34.646297,
                "Y": -3.8962955,
                "Z": -17.257444
              },
              {
                "X": -34.646297,
                "Y": -3.8962975,
                "Z": -2.3962972
              },
              {
                "X": -34.646297,
                "Y": -15.103706,
                "Z": -2.3962955
              },
              {
                "X": -9.519459,
                "Y": 21.230543,
                "Z": 1.4805452
              },
              {
                "X": 18.519451,
                "Y": 21.230543,
                "Z": 1.480545
              },
              {
                "X": 18.519451,
                "Y": 21.230543,
                "Z": 2.8944547
              },
              {
                "X": -9.519461,
                "Y": 21.230543,
                "Z": 2.8944542
              },
              {
                "X": 26.894463,
                "Y": -21.230547,
                "Z": -1.9805331
              },
              {
                "X": 19.230547,
                "Y": -21.230547,
                "Z": -9.644448
              },
              {
                "X": -28.519453,
                "Y": -21.230547,
                "Z": -9.644451
              },
              {
                "X": -28.519457,
                "Y": -21.230547,
                "Z": 3.7305431
              },
              {
                "X": -18.355545,
                "Y": -21.230547,
                "Z": 13.894454
              },
              {
                "X": 26.894459,
                "Y": -21.230547,
                "Z": 13.894458
              },
              {
                "X": -14.987419,
                "Y": 6.8624187,
                "Z": 17.262579
              },
              {
                "X": 23.61242,
                "Y": 6.8624177,
                "Z": 17.262579
              },
              {
                "X": 23.612421,
                "Y": -17.862425,
                "Z": 17.262579
              },
              {
                "X": -14.987425,
                "Y": -17.862421,
                "Z": 17.262579
              },
              {
                "X": 11.612415,
                "Y": -13.6124115,
                "Z": -17.262583
              },
              {
                "X": 11.6124115,
                "Y": 2.4874172,
                "Z": -17.262583
              },
              {
                "X": -28.262585,
                "Y": 2.4874172,
                "Z": -17.262583
              },
              {
                "X": -19.4375,
                "Y": 11.3125,
                "Z": 12.8125
              },
              {
                "X": 28.249996,
                "Y": 11.499999,
                "Z": 12.625001
              },
              {
                "X": 24.437492,
                "Y": 15.312501,
                "Z": -4.437501
              }
            ],
            "IndexData": [
              18,
              1,
              2,
              1,
              0,
              2,
              24,
              13,
              23,
              13,
              18,
              14,
              4,
              23,
              14,
              23,
              13,
              14,
              24,
              1,
              13,
              1,
              18,
              13,
              24,
              0,
              1,
              26,
              25,
              6,
              23,
              4,
              5,
              4,
              6,
              5,
              6,
              25,
              5,
              25,
              23,
              5,
              26,
              9,
              25,
              9,
              24,
              25,
              24,
              23,
              25,
              9,
              26,
              12,
              10,
              9,
              12,
              0,
              10,
              11,
              10,
              12,
              11,
              12,
              26,
              11,
              0,
              24,
              28,
              24,
              10,
              28,
              10,
              0,
              28,
              24,
              9,
              10,
              0,
              11,
              27,
              11,
              20,
              27,
              20,
              2,
              27,
              2,
              0,
              3,
              0,
              27,
              3,
              27,
              2,
              3,
              11,
              26,
              20,
              26,
              6,
              7,
              6,
              8,
              7,
              8,
              26,
              7,
              6,
              4,
              8,
              4,
              14,
              15,
              14,
              16,
              15,
              16,
              4,
              15,
              14,
              17,
              16,
              17,
              8,
              16,
              8,
              4,
              16,
              17,
              26,
              8,
              14,
              18,
              17,
              18,
              21,
              17,
              20,
              26,
              19,
              26,
              17,
              19,
              17,
              21,
              22,
              21,
              19,
              22,
              19,
              17,
              22,
              21,
              20,
              19,
              18,
              2,
              21,
              2,
              20,
              21
            ],
            "ElemBox": {
              "Min": {
                "X": -34.646297,
                "Y": -21.230547,
                "Z": -17.262583
              },
              "Max": {
                "X": 34.646297,
                "Y": 21.230543,
                "Z": 17.262579
              },
              "IsValid": 1
            },
            "Transform": {
              "Rotation": {
                "X": 0.0,
                "Y": 0.0,
                "Z": 0.0,
                "W": 1.0,
                "IsNormalized": true,
                "Size": 1.0,
                "SizeSquared": 1.0
              },
              "Translation": {
                "X": 0.0,
                "Y": 0.0,
                "Z": 0.0
              },
              "Scale3D": {
                "X": 1.0,
                "Y": 1.0,
                "Z": 1.0
              }
            },
            "RestOffset": 0.0,
            "Name": "None",
            "bContributeToMass": true,
            "CollisionEnabled": "ECollisionEnabled::QueryAndPhysics"
          }
        ]
      },
      "DefaultInstance": {
        "ObjectType": "ECC_WorldStatic",
        "CollisionProfileName": "BlockAll",
        "CollisionResponses": {
          "ResponseArray": [
            {
              "Channel": "Broom",
              "Response": "ECR_Block"
            },
            {
              "Channel": "LargeDestructible",
              "Response": "ECR_Block"
            },
            {
              "Channel": "FootIK",
              "Response": "ECR_Block"
            },
            {
              "Channel": "MapTrace",
              "Response": "ECR_Block"
            },
            {
              "Channel": "InteractBlockers",
              "Response": "ECR_Block"
            },
            {
              "Channel": "EdgeCheck",
              "Response": "ECR_Block"
            }
          ]
        }
      }
    },
    "BodySetupGuid": "A732D7904ADC16410A5990818C662959",
    "CookedFormatData": {
      "PhysXPC": {
        "BulkDataFlags": "BULKDATA_SingleUse | BULKDATA_ForceInlinePayload",
        "ElementCount": 2368,
        "SizeOnDisk": 2368,
        "OffsetInFile": "0x4AB9"
      }
    }
  },
  {
    "Type": "NavCollision",
    "Name": "NavCollision_0",
    "Outer": "VFX_SM_Troll_Pro_Split_C",
    "Class": "UScriptClass'NavCollision'",
    "CookedFormatData": {
      "NavCollision_Chaos": {
        "BulkDataFlags": "BULKDATA_SingleUse | BULKDATA_ForceInlinePayload",
        "ElementCount": 1021,
        "SizeOnDisk": 1021,
        "OffsetInFile": "0x5441"
      }
    }
  },
  {
    "Type": "StaticMesh",
    "Name": "VFX_SM_Troll_Pro_Split_C",
    "Class": "UScriptClass'StaticMesh'",
    "Properties": {
      "MinLOD": {
        "bCooked": true,
        "Default": 0,
        "Value": 0
      },
      "StaticMaterials": [
        {
          "MaterialInterface": {
            "ObjectName": "MaterialInstanceConstant'VFX_MI_TrollRock'",
            "ObjectPath": "/Game/VFX/Enemies/Troll/Troll_Rock_Toss/Projectile/VFX_MI_TrollRock.0"
          },
          "MaterialSlotName": "lambert1",
          "ImportedMaterialSlotName": "lambert1",
          "UVChannelData": {
            "bInitialized": true,
            "bOverrideDensities": false,
            "LocalUVDensities": 134.64757,
            "LocalUVDensities": 0.0,
            "LocalUVDensities": 0.0,
            "LocalUVDensities": 0.0
          }
        }
      ],
      "LightmapUVDensity": 134.64757,
      "LightMapResolution": 32,
      "ExtendedBounds": {
        "BoxExtent": {
          "X": 34.5463,
          "Y": 21.130547,
          "Z": 17.162582
        },
        "SphereRadius": 40.878376
      }
    },
    "BodySetup": {
      "ObjectName": "BodySetup'VFX_SM_Troll_Pro_Split_C:BodySetup_0'",
      "ObjectPath": "/Game/VFX/Enemies/Troll/Troll_Rock_Toss/Projectile/VFX_SM_Troll_Pro_Split_C.0"
    },
    "NavCollision": {
      "ObjectName": "NavCollision'VFX_SM_Troll_Pro_Split_C:NavCollision_0'",
      "ObjectPath": "/Game/VFX/Enemies/Troll/Troll_Rock_Toss/Projectile/VFX_SM_Troll_Pro_Split_C.1"
    },
    "LightingGuid": "29FF029C-454A6F15-6A9F6096-0AB30E2E",
    "RenderData": {
      "LODs": [
        {
          "Sections": [
            {
              "MaterialIndex": 0,
              "FirstIndex": 0,
              "NumTriangles": 112,
              "MinVertexIndex": 0,
              "MaxVertexIndex": 127,
              "bEnableCollision": true,
              "bCastShadow": true,
              "bForceOpaque": false,
              "bVisibleInRayTracing": true
            }
          ],
          "MaxDeviation": 0.0,
          "PositionVertexBuffer": {
            "Stride": 12,
            "NumVertices": 128
          },
          "VertexBuffer": {
            "NumTexCoords": 1,
            "NumVertices": 128,
            "Strides": -1,
            "UseHighPrecisionTangentBasis": false,
            "UseFullPrecisionUVs": false
          },
          "ColorVertexBuffer": {
            "Stride": 4,
            "NumVertices": 128
          }
        },
        {
          "Sections": [
            {
              "MaterialIndex": 0,
              "FirstIndex": 0,
              "NumTriangles": 56,
              "MinVertexIndex": 0,
              "MaxVertexIndex": 80,
              "bEnableCollision": true,
              "bCastShadow": true,
              "bForceOpaque": false,
              "bVisibleInRayTracing": true
            }
          ],
          "MaxDeviation": 17.762188,
          "PositionVertexBuffer": {
            "Stride": 12,
            "NumVertices": 81
          },
          "VertexBuffer": {
            "NumTexCoords": 1,
            "NumVertices": 81,
            "Strides": -1,
            "UseHighPrecisionTangentBasis": false,
            "UseFullPrecisionUVs": false
          },
          "ColorVertexBuffer": {
            "Stride": 4,
            "NumVertices": 81
          }
        }
      ],
      "Bounds": {
        "Origin": {
          "X": 0.0,
          "Y": 0.0,
          "Z": 0.0
        },
        "BoxExtent": {
          "X": 34.5463,
          "Y": 21.130547,
          "Z": 17.162582
        },
        "SphereRadius": 40.878376
      },
      "bLODsShareStaticLighting": true,
      "ScreenSize": [
        0.027317334,
        "NaN",
        0.023658667,
        "NaN",
        0.0,
        "NaN",
        0.0,
        "NaN"
      ]
    }
  }
]