[
  {
    "Type": "AnimSequence",
    "Name": "CQT_FLY_01_01_Up_Shot_010_Student01_anm",
    "Class": "UScriptClass'AnimSequence'",
    "ClassPath": "/Script/Engine.AnimSequence",
    "Properties": {
      "NumFrames": 100,
      "TrackToSkeletonMapTable": [
        {
          "BoneTreeIndex": 0
        },
        {
          "BoneTreeIndex": 132
        },
        {
          "BoneTreeIndex": 131
        },
        {
          "BoneTreeIndex": 1
        },
        {
          "BoneTreeIndex": 115
        },
        {
          "BoneTreeIndex": 2
        },
        {
          "BoneTreeIndex": 84
        },
        {
          "BoneTreeIndex": 85
        },
        {
          "BoneTreeIndex": 86
        },
        {
          "BoneTreeIndex": 177
        },
        {
          "BoneTreeIndex": 87
        },
        {
          "BoneTreeIndex": 88
        },
        {
          "BoneTreeIndex": 89
        },
        {
          "BoneTreeIndex": 90
        },
        {
          "BoneTreeIndex": 171
        },
        {
          "BoneTreeIndex": 130
        },
        {
          "BoneTreeIndex": 4
        },
        {
          "BoneTreeIndex": 5
        },
        {
          "BoneTreeIndex": 6
        },
        {
          "BoneTreeIndex": 172
        },
        {
          "BoneTreeIndex": 7
        },
        {
          "BoneTreeIndex": 8
        },
        {
          "BoneTreeIndex": 9
        },
        {
          "BoneTreeIndex": 10
        },
        {
          "BoneTreeIndex": 166
        },
        {
          "BoneTreeIndex": 3
        },
        {
          "BoneTreeIndex": 11
        },
        {
          "BoneTreeIndex": 12
        },
        {
          "BoneTreeIndex": 13
        },
        {
          "BoneTreeIndex": 176
        },
        {
          "BoneTreeIndex": 14
        },
        {
          "BoneTreeIndex": 20
        },
        {
          "BoneTreeIndex": 21
        },
        {
          "BoneTreeIndex": 22
        },
        {
          "BoneTreeIndex": 23
        },
        {
          "BoneTreeIndex": 24
        },
        {
          "BoneTreeIndex": 167
        },
        {
          "BoneTreeIndex": 26
        },
        {
          "BoneTreeIndex": 37
        },
        {
          "BoneTreeIndex": 38
        },
        {
          "BoneTreeIndex": 39
        },
        {
          "BoneTreeIndex": 40
        },
        {
          "BoneTreeIndex": 41
        },
        {
          "BoneTreeIndex": 36
        },
        {
          "BoneTreeIndex": 42
        },
        {
          "BoneTreeIndex": 43
        },
        {
          "BoneTreeIndex": 44
        },
        {
          "BoneTreeIndex": 45
        },
        {
          "BoneTreeIndex": 46
        },
        {
          "BoneTreeIndex": 128
        },
        {
          "BoneTreeIndex": 31
        },
        {
          "BoneTreeIndex": 32
        },
        {
          "BoneTreeIndex": 33
        },
        {
          "BoneTreeIndex": 34
        },
        {
          "BoneTreeIndex": 35
        },
        {
          "BoneTreeIndex": 27
        },
        {
          "BoneTreeIndex": 28
        },
        {
          "BoneTreeIndex": 29
        },
        {
          "BoneTreeIndex": 30
        },
        {
          "BoneTreeIndex": 47
        },
        {
          "BoneTreeIndex": 48
        },
        {
          "BoneTreeIndex": 49
        },
        {
          "BoneTreeIndex": 50
        },
        {
          "BoneTreeIndex": 51
        },
        {
          "BoneTreeIndex": 25
        },
        {
          "BoneTreeIndex": 168
        },
        {
          "BoneTreeIndex": 174
        },
        {
          "BoneTreeIndex": 52
        },
        {
          "BoneTreeIndex": 163
        },
        {
          "BoneTreeIndex": 15
        },
        {
          "BoneTreeIndex": 16
        },
        {
          "BoneTreeIndex": 17
        },
        {
          "BoneTreeIndex": 18
        },
        {
          "BoneTreeIndex": 19
        },
        {
          "BoneTreeIndex": 173
        },
        {
          "BoneTreeIndex": 53
        },
        {
          "BoneTreeIndex": 54
        },
        {
          "BoneTreeIndex": 55
        },
        {
          "BoneTreeIndex": 57
        },
        {
          "BoneTreeIndex": 129
        },
        {
          "BoneTreeIndex": 58
        },
        {
          "BoneTreeIndex": 59
        },
        {
          "BoneTreeIndex": 60
        },
        {
          "BoneTreeIndex": 61
        },
        {
          "BoneTreeIndex": 78
        },
        {
          "BoneTreeIndex": 79
        },
        {
          "BoneTreeIndex": 80
        },
        {
          "BoneTreeIndex": 81
        },
        {
          "BoneTreeIndex": 82
        },
        {
          "BoneTreeIndex": 67
        },
        {
          "BoneTreeIndex": 73
        },
        {
          "BoneTreeIndex": 74
        },
        {
          "BoneTreeIndex": 75
        },
        {
          "BoneTreeIndex": 76
        },
        {
          "BoneTreeIndex": 77
        },
        {
          "BoneTreeIndex": 68
        },
        {
          "BoneTreeIndex": 69
        },
        {
          "BoneTreeIndex": 70
        },
        {
          "BoneTreeIndex": 71
        },
        {
          "BoneTreeIndex": 72
        },
        {
          "BoneTreeIndex": 62
        },
        {
          "BoneTreeIndex": 63
        },
        {
          "BoneTreeIndex": 64
        },
        {
          "BoneTreeIndex": 65
        },
        {
          "BoneTreeIndex": 66
        },
        {
          "BoneTreeIndex": 169
        },
        {
          "BoneTreeIndex": 170
        },
        {
          "BoneTreeIndex": 56
        },
        {
          "BoneTreeIndex": 175
        },
        {
          "BoneTreeIndex": 83
        },
        {
          "BoneTreeIndex": 164
        },
        {
          "BoneTreeIndex": 179
        },
        {
          "BoneTreeIndex": 180
        },
        {
          "BoneTreeIndex": 181
        },
        {
          "BoneTreeIndex": 182
        },
        {
          "BoneTreeIndex": 178
        },
        {
          "BoneTreeIndex": 97
        },
        {
          "BoneTreeIndex": 96
        },
        {
          "BoneTreeIndex": 95
        },
        {
          "BoneTreeIndex": 94
        },
        {
          "BoneTreeIndex": 93
        },
        {
          "BoneTreeIndex": 92
        },
        {
          "BoneTreeIndex": 91
        }
      ],
      "BoneCompressionSettings": {
        "ObjectName": "AnimBoneCompressionSettings'AC_PhxAnimBoneCompressionSettings_Cinematic'",
        "ObjectPath": "/Game/Animation/Settings/AC_PhxAnimBoneCompressionSettings_Cinematic.2"
      },
      "CurveCompressionSettings": {
        "ObjectName": "AnimCurveCompressionSettings'AC_PhxAnimCurveCompressionSettings'",
        "ObjectPath": "/Game/Animation/Settings/AC_PhxAnimCurveCompressionSettings.1"
      },
      "SequenceLength": 3.3,
      "Skeleton": {
        "ObjectName": "Skeleton'Biped_Skeleton'",
        "ObjectPath": "/Game/RiggedObjects/Characters/Biped_Skeleton.76"
      },
      "AssetUserData": [
        null,
        null,
        null
      ]
    },
    "SkeletonGuid": "EF6C01A3-4D5FA308-79BBC883-146F08EB",
    "CompressedTrackToSkeletonMapTable": [
      0,
      132,
      131,
      1,
      115,
      2,
      84,
      85,
      86,
      177,
      87,
      88,
      89,
      90,
      171,
      130,
      4,
      5,
      6,
      172,
      7,
      8,
      9,
      10,
      166,
      3,
      11,
      12,
      13,
      176,
      14,
      20,
      21,
      22,
      23,
      24,
      167,
      26,
      37,
      38,
      39,
      40,
      41,
      36,
      42,
      43,
      44,
      45,
      46,
      128,
      31,
      32,
      33,
      34,
      35,
      27,
      28,
      29,
      30,
      47,
      48,
      49,
      50,
      51,
      25,
      168,
      174,
      52,
      163,
      15,
      16,
      17,
      18,
      19,
      173,
      53,
      54,
      55,
      57,
      129,
      58,
      59,
      60,
      61,
      78,
      79,
      80,
      81,
      82,
      67,
      73,
      74,
      75,
      76,
      77,
      68,
      69,
      70,
      71,
      72,
      62,
      63,
      64,
      65,
      66,
      169,
      170,
      56,
      175,
      83,
      164,
      179,
      180,
      181,
      182,
      178,
      97,
      96,
      95,
      94,
      93,
      92,
      91,
      260,
      261,
      262,
      263,
      264,
      265,
      266
    ],
    "CompressedCurveNames": [
      {
        "DisplayName": "TimeToPhase"
      },
      {
        "DisplayName": "PhaseToTime"
      },
      {
        "DisplayName": "FootPlants"
      },
      {
        "DisplayName": "Speed"
      },
      {
        "DisplayName": "SpeedToTime"
      },
      {
        "DisplayName": "AverageSpeed"
      }
    ],
    "CompressedCurveData": {
      "FloatCurves": [
        {
          "FloatCurve": {
            "Keys": [
              {
                "InterpMode": "RCIM_Linear",
                "TangentMode": "RCTM_Auto",
                "TangentWeightMode": "RCTWM_WeightedNone",
                "Time": 0.0,
                "Value": 0.38233036,
                "ArriveTangent": 0.3919369,
                "ArriveTangentWeight": 0.0,
                "LeaveTangent": 0.39902973,
                "LeaveTangentWeight": 0.0
              },
              {
                "InterpMode": "RCIM_Linear",
                "TangentMode": "RCTM_Auto",
                "TangentWeightMode": "RCTWM_WeightedNone",
                "Time": 0.033333335,
                "Value": 0.3919369,
                "ArriveTangent": 0.39902973,
                "ArriveTangentWeight": 0.0,
                "LeaveTangent": 0.4023013,
                "LeaveTangentWeight": 0.0
              },
              {
                "InterpMode": "RCIM_Linear",
                "TangentMode": "RCTM_Auto",
                "TangentWeightMode": "RCTWM_WeightedNone",
                "Time": 0.06666667,
                "Value": 0.39902973,
                "ArriveTangent": 0.4023013,
                "ArriveTangentWeight": 0.0,
                "LeaveTangent": 0.40254682,
                "LeaveTangentWeight": 0.0
              },
              {
                "InterpMode": "RCIM_Linear",
                "TangentMode": "RCTM_Auto",
                "TangentWeightMode": "RCTWM_WeightedNone",
                "Time": 0.10000001,
                "Value": 0.4023013,
                "ArriveTangent": 0.40254682,
                "ArriveTangentWeight": 0.0,
                "LeaveTangent": 0.39738062,
                "LeaveTangentWeight": 0.0
              },
              {
                "InterpMode": "RCIM_Linear",
                "TangentMode": "RCTM_Auto",
                "TangentWeightMode": "RCTWM_WeightedNone",
                "Time": 0.13333334,
                "Value": 0.40254682,
                "ArriveTangent": 0.39738062,
                "ArriveTangentWeight": 0.0,
                "LeaveTangent": 0.37821552,
                "LeaveTangentWeight": 0.0
              },
              {
                "InterpMode": "RCIM_Linear",
                "TangentMode": "RCTM_Auto",
                "TangentWeightMode": "RCTWM_WeightedNone",
                "Time": 0.20000002,
                "Value": 0.39738062,
                "ArriveTangent": 0.37821552,
                "ArriveTangentWeight": 0.0,
                "LeaveTangent": 0.37152833,
                "LeaveTangentWeight": 0.0
              },
              {
                "InterpMode": "RCIM_Linear",
                "TangentMode": "RCTM_Auto",
                "TangentWeightMode": "RCTWM_WeightedNone",
                "Time": 0.33333334,
                "Value": 0.37821552,
                "ArriveTangent": 0.37152833,
                "ArriveTangentWeight": 0.0,
                "LeaveTangent": 0.3653748,
                "LeaveTangentWeight": 0.0
              },
              {
                "InterpMode": "RCIM_Linear",
                "TangentMode": "RCTM_Auto",
                "TangentWeightMode": "RCTWM_WeightedNone",
                "Time": 0.4666667,
                "Value": 0.37152833,
                "ArriveTangent": 0.3653748,
                "ArriveTangentWeight": 0.0,
                "LeaveTangent": 0.353927,
                "LeaveTangentWeight": 0.0
              },
              {
                "InterpMode": "RCIM_Linear",
                "TangentMode": "RCTM_Auto",
                "TangentWeightMode": "RCTWM_WeightedNone",
                "Time": 0.5,
                "Value": 0.3653748,
                "ArriveTangent": 0.353927,
                "ArriveTangentWeight": 0.0,
                "LeaveTangent": 0.3259132,
                "LeaveTangentWeight": 0.0
              },
              {
                "InterpMode": "RCIM_Linear",
                "TangentMode": "RCTM_Auto",
                "TangentWeightMode": "RCTWM_WeightedNone",
                "Time": 0.53333336,
                "Value": 0.353927,
                "ArriveTangent": 0.3259132,
                "ArriveTangentWeight": 0.0,
                "LeaveTangent": 0.31404907,
                "LeaveTangentWeight": 0.0
              },
              {
                "InterpMode": "RCIM_Linear",
                "TangentMode": "RCTM_Auto",
                "TangentWeightMode": "RCTWM_WeightedNone",
                "Time": 0.6,
                "Value": 0.3259132,
                "ArriveTangent": 0.31404907,
                "ArriveTangentWeight": 0.0,
                "LeaveTangent": 0.30643854,
                "LeaveTangentWeight": 0.0
              },
              {
                "InterpMode": "RCIM_Linear",
                "TangentMode": "RCTM_Auto",
                "TangentWeightMode": "RCTWM_WeightedNone",
                "Time": 0.6333334,
                "Value": 0.31404907,
                "ArriveTangent": 0.30643854,
                "ArriveTangentWeight": 0.0,
                "LeaveTangent": 0.3023184,
                "LeaveTangentWeight": 0.0
              },
              {
                "InterpMode": "RCIM_Linear",
                "TangentMode": "RCTM_Auto",
                "TangentWeightMode": "RCTWM_WeightedNone",
                "Time": 0.6666667,
                "Value": 0.30643854,
                "ArriveTangent": 0.3023184,
                "ArriveTangentWeight": 0.0,
                "LeaveTangent": 0.29578596,
                "LeaveTangentWeight": 0.0
              },
              {
                "InterpMode": "RCIM_Linear",
                "TangentMode": "RCTM_Auto",
                "TangentWeightMode": "RCTWM_WeightedNone",
                "Time": 0.70000005,
                "Value": 0.3023184,
                "ArriveTangent": 0.29578596,
                "ArriveTangentWeight": 0.0,
                "LeaveTangent": 0.2799725,
                "LeaveTangentWeight": 0.0
              },
              {
                "InterpMode": "RCIM_Linear",
                "TangentMode": "RCTM_Auto",
                "TangentWeightMode": "RCTWM_WeightedNone",
                "Time": 0.8000001,
                "Value": 0.29578596,
                "ArriveTangent": 0.2799725,
                "ArriveTangentWeight": 0.0,
                "LeaveTangent": 0.27862757,
                "LeaveTangentWeight": 0.0
              },
              {
                "InterpMode": "RCIM_Linear",
                "TangentMode": "RCTM_Auto",
                "TangentWeightMode": "RCTWM_WeightedNone",
                "Time": 0.90000004,
                "Value": 0.2799725,
                "ArriveTangent": 0.27862757,
                "ArriveTangentWeight": 0.0,
                "LeaveTangent": 0.29127622,
                "LeaveTangentWeight": 0.0
              },
              {
                "InterpMode": "RCIM_Linear",
                "TangentMode": "RCTM_Auto",
                "TangentWeightMode": "RCTWM_WeightedNone",
                "Time": 0.9333334,
                "Value": 0.27862757,
                "ArriveTangent": 0.29127622,
                "ArriveTangentWeight": 0.0,
                "LeaveTangent": 0.2963303,
                "LeaveTangentWeight": 0.0
              },
              {
                "InterpMode": "RCIM_Linear",
                "TangentMode": "RCTM_Auto",
                "TangentWeightMode": "RCTWM_WeightedNone",
                "Time": 1.1,
                "Value": 0.29127622,
                "ArriveTangent": 0.2963303,
                "ArriveTangentWeight": 0.0,
                "LeaveTangent": 0.30963007,
                "LeaveTangentWeight": 0.0
              },
              {
                "InterpMode": "RCIM_Linear",
                "TangentMode": "RCTM_Auto",
                "TangentWeightMode": "RCTWM_WeightedNone",
                "Time": 1.2333333,
                "Value": 0.2963303,
                "ArriveTangent": 0.30963007,
                "ArriveTangentWeight": 0.0,
                "LeaveTangent": 0.3099823,
                "LeaveTangentWeight": 0.0
              },
              {
                "InterpMode": "RCIM_Linear",
                "TangentMode": "RCTM_Auto",
                "TangentWeightMode": "RCTWM_WeightedNone",
                "Time": 1.3666668,
                "Value": 0.30963007,
                "ArriveTangent": 0.3099823,
                "ArriveTangentWeight": 0.0,
                "LeaveTangent": 0.29337364,
                "LeaveTangentWeight": 0.0
              },
              {
                "InterpMode": "RCIM_Linear",
                "TangentMode": "RCTM_Auto",
                "TangentWeightMode": "RCTWM_WeightedNone",
                "Time": 1.4333334,
                "Value": 0.3099823,
                "ArriveTangent": 0.29337364,
                "ArriveTangentWeight": 0.0,
                "LeaveTangent": 0.28510666,
                "LeaveTangentWeight": 0.0
              },
              {
                "InterpMode": "RCIM_Linear",
                "TangentMode": "RCTM_Auto",
                "TangentWeightMode": "RCTWM_WeightedNone",
                "Time": 1.7,
                "Value": 0.29337364,
                "ArriveTangent": 0.28510666,
                "ArriveTangentWeight": 0.0,
                "LeaveTangent": 0.19481033,
                "LeaveTangentWeight": 0.0
              },
              {
                "InterpMode": "RCIM_Linear",
                "TangentMode": "RCTM_Auto",
                "TangentWeightMode": "RCTWM_WeightedNone",
                "Time": 1.7666668,
                "Value": 0.28510666,
                "ArriveTangent": 0.19481033,
                "ArriveTangentWeight": 0.0,
                "LeaveTangent": 0.15152746,
                "LeaveTangentWeight": 0.0
              },
              {
                "InterpMode": "RCIM_Linear",
                "TangentMode": "RCTM_Auto",
                "TangentWeightMode": "RCTWM_WeightedNone",
                "Time": 2.1333334,
                "Value": 0.19481033,
                "ArriveTangent": 0.15152746,
                "ArriveTangentWeight": 0.0,
                "LeaveTangent": 0.13632774,
                "LeaveTangentWeight": 0.0
              },
              {
                "InterpMode": "RCIM_Linear",
                "TangentMode": "RCTM_Auto",
                "TangentWeightMode": "RCTWM_WeightedNone",
                "Time": 2.266667,
                "Value": 0.15152746,
                "ArriveTangent": 0.13632774,
                "ArriveTangentWeight": 0.0,
                "LeaveTangent": 0.12635294,
                "LeaveTangentWeight": 0.0
              },
              {
                "InterpMode": "RCIM_Linear",
                "TangentMode": "RCTM_Auto",
                "TangentWeightMode": "RCTWM_WeightedNone",
                "Time": 2.3333335,
                "Value": 0.13632774,
                "ArriveTangent": 0.12635294,
                "ArriveTangentWeight": 0.0,
                "LeaveTangent": 0.1018242,
                "LeaveTangentWeight": 0.0
              },
              {
                "InterpMode": "RCIM_Linear",
                "TangentMode": "RCTM_Auto",
                "TangentWeightMode": "RCTWM_WeightedNone",
                "Time": 2.4,
                "Value": 0.12635294,
                "ArriveTangent": 0.1018242,
                "ArriveTangentWeight": 0.0,
                "LeaveTangent": 0.099161066,
                "LeaveTangentWeight": 0.0
              },
              {
                "InterpMode": "RCIM_Linear",
                "TangentMode": "RCTM_Auto",
                "TangentWeightMode": "RCTWM_WeightedNone",
                "Time": 2.6666667,
                "Value": 0.1018242,
                "ArriveTangent": 0.099161066,
                "ArriveTangentWeight": 0.0,
                "LeaveTangent": 0.1024913,
                "LeaveTangentWeight": 0.0
              },
              {
                "InterpMode": "RCIM_Linear",
                "TangentMode": "RCTM_Auto",
                "TangentWeightMode": "RCTWM_WeightedNone",
                "Time": 2.766667,
                "Value": 0.099161066,
                "ArriveTangent": 0.1024913,
                "ArriveTangentWeight": 0.0,
                "LeaveTangent": 0.11220459,
                "LeaveTangentWeight": 0.0
              },
              {
                "InterpMode": "RCIM_Linear",
                "TangentMode": "RCTM_Auto",
                "TangentWeightMode": "RCTWM_WeightedNone",
                "Time": 2.8333335,
                "Value": 0.1024913,
                "ArriveTangent": 0.11220459,
                "ArriveTangentWeight": 0.0,
                "LeaveTangent": 0.12799671,
                "LeaveTangentWeight": 0.0
              },
              {
                "InterpMode": "RCIM_Linear",
                "TangentMode": "RCTM_Auto",
                "TangentWeightMode": "RCTWM_WeightedNone",
                "Time": 2.9,
                "Value": 0.11220459,
                "ArriveTangent": 0.12799671,
                "ArriveTangentWeight": 0.0,
                "LeaveTangent": 0.15915933,
                "LeaveTangentWeight": 0.0
              },
              {
                "InterpMode": "RCIM_Linear",
                "TangentMode": "RCTM_Auto",
                "TangentWeightMode": "RCTWM_WeightedNone",
                "Time": 2.966667,
                "Value": 0.12799671,
                "ArriveTangent": 0.15915933,
                "ArriveTangentWeight": 0.0,
                "LeaveTangent": 0.24997866,
                "LeaveTangentWeight": 0.0
              },
              {
                "InterpMode": "RCIM_Linear",
                "TangentMode": "RCTM_Auto",
                "TangentWeightMode": "RCTWM_WeightedNone",
                "Time": 3.0666668,
                "Value": 0.15915933,
                "ArriveTangent": 0.24997866,
                "ArriveTangentWeight": 0.0,
                "LeaveTangent": 0.0,
                "LeaveTangentWeight": 0.0
              },
              {
                "InterpMode": "RCIM_Linear",
                "TangentMode": "RCTM_Auto",
                "TangentWeightMode": "RCTWM_WeightedNone",
                "Time": 3.3000002,
                "Value": 0.24997866,
                "ArriveTangent": 0.0,
                "ArriveTangentWeight": 0.0,
                "LeaveTangent": 0.028967569,
                "LeaveTangentWeight": 0.0
              }
            ],
            "DefaultValue": 3.4028235E+38,
            "PreInfinityExtrap": "RCCE_Constant",
            "PostInfinityExtrap": "RCCE_Constant"
          },
          "Name": {
            "DisplayName": "TimeToPhase"
          },
          "CurveTypeFlags": 4
        },
        {
          "FloatCurve": {
            "Keys": [
              {
                "InterpMode": "RCIM_Linear",
                "TangentMode": "RCTM_Auto",
                "TangentWeightMode": "RCTWM_WeightedNone",
                "Time": 0.0,
                "Value": 2.766667,
                "ArriveTangent": 2.6666667,
                "ArriveTangentWeight": 0.0,
                "LeaveTangent": 2.4,
                "LeaveTangentWeight": 0.0
              },
              {
                "InterpMode": "RCIM_Linear",
                "TangentMode": "RCTM_Auto",
                "TangentWeightMode": "RCTWM_WeightedNone",
                "Time": 0.028967569,
                "Value": 2.6666667,
                "ArriveTangent": 2.4,
                "ArriveTangentWeight": 0.0,
                "LeaveTangent": 2.3333335,
                "LeaveTangentWeight": 0.0
              },
              {
                "InterpMode": "RCIM_Linear",
                "TangentMode": "RCTM_Auto",
                "TangentWeightMode": "RCTWM_WeightedNone",
                "Time": 0.29577252,
                "Value": 2.4,
                "ArriveTangent": 2.3333335,
                "ArriveTangentWeight": 0.0,
                "LeaveTangent": 2.266667,
                "LeaveTangentWeight": 0.0
              },
              {
                "InterpMode": "RCIM_Linear",
                "TangentMode": "RCTM_Auto",
                "TangentWeightMode": "RCTWM_WeightedNone",
                "Time": 0.40427092,
                "Value": 2.3333335,
                "ArriveTangent": 2.266667,
                "ArriveTangentWeight": 0.0,
                "LeaveTangent": 2.1333334,
                "LeaveTangentWeight": 0.0
              },
              {
                "InterpMode": "RCIM_Linear",
                "TangentMode": "RCTM_Auto",
                "TangentWeightMode": "RCTWM_WeightedNone",
                "Time": 0.56960195,
                "Value": 2.266667,
                "ArriveTangent": 2.1333334,
                "ArriveTangentWeight": 0.0,
                "LeaveTangent": 0.9333334,
                "LeaveTangentWeight": 0.0
              },
              {
                "InterpMode": "RCIM_Linear",
                "TangentMode": "RCTM_Auto",
                "TangentWeightMode": "RCTWM_WeightedNone",
                "Time": 1.0404001,
                "Value": 2.1333334,
                "ArriveTangent": 0.9333334,
                "ArriveTangentWeight": 0.0,
                "LeaveTangent": 0.90000004,
                "LeaveTangentWeight": 0.0
              },
              {
                "InterpMode": "RCIM_Linear",
                "TangentMode": "RCTM_Auto",
                "TangentWeightMode": "RCTWM_WeightedNone",
                "Time": 1.9521005,
                "Value": 0.9333334,
                "ArriveTangent": 0.90000004,
                "ArriveTangentWeight": 0.0,
                "LeaveTangent": 0.8000001,
                "LeaveTangentWeight": 0.0
              },
              {
                "InterpMode": "RCIM_Linear",
                "TangentMode": "RCTM_Auto",
                "TangentWeightMode": "RCTWM_WeightedNone",
                "Time": 1.9667295,
                "Value": 0.90000004,
                "ArriveTangent": 0.8000001,
                "ArriveTangentWeight": 0.0,
                "LeaveTangent": 0.70000005,
                "LeaveTangentWeight": 0.0
              },
              {
                "InterpMode": "RCIM_Linear",
                "TangentMode": "RCTM_Auto",
                "TangentWeightMode": "RCTWM_WeightedNone",
                "Time": 2.1387365,
                "Value": 0.8000001,
                "ArriveTangent": 0.70000005,
                "ArriveTangentWeight": 0.0,
                "LeaveTangent": 0.6666667,
                "LeaveTangentWeight": 0.0
              },
              {
                "InterpMode": "RCIM_Linear",
                "TangentMode": "RCTM_Auto",
                "TangentWeightMode": "RCTWM_WeightedNone",
                "Time": 2.2097912,
                "Value": 0.70000005,
                "ArriveTangent": 0.6666667,
                "ArriveTangentWeight": 0.0,
                "LeaveTangent": 0.6333334,
                "LeaveTangentWeight": 0.0
              },
              {
                "InterpMode": "RCIM_Linear",
                "TangentMode": "RCTM_Auto",
                "TangentWeightMode": "RCTWM_WeightedNone",
                "Time": 2.2546072,
                "Value": 0.6666667,
                "ArriveTangent": 0.6333334,
                "ArriveTangentWeight": 0.0,
                "LeaveTangent": 0.6,
                "LeaveTangentWeight": 0.0
              },
              {
                "InterpMode": "RCIM_Linear",
                "TangentMode": "RCTM_Auto",
                "TangentWeightMode": "RCTWM_WeightedNone",
                "Time": 2.3373888,
                "Value": 0.6333334,
                "ArriveTangent": 0.6,
                "ArriveTangentWeight": 0.0,
                "LeaveTangent": 0.53333336,
                "LeaveTangentWeight": 0.0
              },
              {
                "InterpMode": "RCIM_Linear",
                "TangentMode": "RCTM_Auto",
                "TangentWeightMode": "RCTWM_WeightedNone",
                "Time": 2.4664376,
                "Value": 0.6,
                "ArriveTangent": 0.53333336,
                "ArriveTangentWeight": 0.0,
                "LeaveTangent": 0.5,
                "LeaveTangentWeight": 0.0
              },
              {
                "InterpMode": "RCIM_Linear",
                "TangentMode": "RCTM_Auto",
                "TangentWeightMode": "RCTWM_WeightedNone",
                "Time": 2.7711506,
                "Value": 0.53333336,
                "ArriveTangent": 0.5,
                "ArriveTangentWeight": 0.0,
                "LeaveTangent": 0.4666667,
                "LeaveTangentWeight": 0.0
              },
              {
                "InterpMode": "RCIM_Linear",
                "TangentMode": "RCTM_Auto",
                "TangentWeightMode": "RCTWM_WeightedNone",
                "Time": 2.8956711,
                "Value": 0.5,
                "ArriveTangent": 0.4666667,
                "ArriveTangentWeight": 0.0,
                "LeaveTangent": 0.33333334,
                "LeaveTangentWeight": 0.0
              },
              {
                "InterpMode": "RCIM_Linear",
                "TangentMode": "RCTM_Auto",
                "TangentWeightMode": "RCTWM_WeightedNone",
                "Time": 2.9626045,
                "Value": 0.4666667,
                "ArriveTangent": 0.33333334,
                "ArriveTangentWeight": 0.0,
                "LeaveTangent": 0.0,
                "LeaveTangentWeight": 0.0
              },
              {
                "InterpMode": "RCIM_Linear",
                "TangentMode": "RCTM_Auto",
                "TangentWeightMode": "RCTWM_WeightedNone",
                "Time": 3.0353427,
                "Value": 0.33333334,
                "ArriveTangent": 0.0,
                "ArriveTangentWeight": 0.0,
                "LeaveTangent": 0.033333335,
                "LeaveTangentWeight": 0.0
              },
              {
                "InterpMode": "RCIM_Linear",
                "TangentMode": "RCTM_Auto",
                "TangentWeightMode": "RCTWM_WeightedNone",
                "Time": 3.080101,
                "Value": 0.0,
                "ArriveTangent": 0.033333335,
                "ArriveTangentWeight": 0.0,
                "LeaveTangent": 0.06666667,
                "LeaveTangentWeight": 0.0
              },
              {
                "InterpMode": "RCIM_Linear",
                "TangentMode": "RCTM_Auto",
                "TangentWeightMode": "RCTWM_WeightedNone",
                "Time": 3.1845934,
                "Value": 0.033333335,
                "ArriveTangent": 0.06666667,
                "ArriveTangentWeight": 0.0,
                "LeaveTangent": 0.10000001,
                "LeaveTangentWeight": 0.0
              },
              {
                "InterpMode": "RCIM_Linear",
                "TangentMode": "RCTM_Auto",
                "TangentWeightMode": "RCTWM_WeightedNone",
                "Time": 3.261744,
                "Value": 0.06666667,
                "ArriveTangent": 0.10000001,
                "ArriveTangentWeight": 0.0,
                "LeaveTangent": 0.13333334,
                "LeaveTangentWeight": 0.0
              },
              {
                "InterpMode": "RCIM_Linear",
                "TangentMode": "RCTM_Auto",
                "TangentWeightMode": "RCTWM_WeightedNone",
                "Time": 3.2973297,
                "Value": 0.10000001,
                "ArriveTangent": 0.13333334,
                "ArriveTangentWeight": 0.0,
                "LeaveTangent": 0.0,
                "LeaveTangentWeight": 0.0
              },
              {
                "InterpMode": "RCIM_Linear",
                "TangentMode": "RCTM_Auto",
                "TangentWeightMode": "RCTWM_WeightedNone",
                "Time": 3.3000002,
                "Value": 0.13333334,
                "ArriveTangent": 0.0,
                "ArriveTangentWeight": 0.0,
                "LeaveTangent": 0.033333335,
                "LeaveTangentWeight": 0.0
              }
            ],
            "DefaultValue": 3.4028235E+38,
            "PreInfinityExtrap": "RCCE_Constant",
            "PostInfinityExtrap": "RCCE_Constant"
          },
          "Name": {
            "DisplayName": "PhaseToTime"
          },
          "CurveTypeFlags": 4
        },
        {
          "FloatCurve": {
            "Keys": [
              {
                "InterpMode": "RCIM_Linear",
                "TangentMode": "RCTM_Auto",
                "TangentWeightMode": "RCTWM_WeightedNone",
                "Time": 0.0,
                "Value": 3.0,
                "ArriveTangent": 0.0,
                "ArriveTangentWeight": 0.0,
                "LeaveTangent": 0.0,
                "LeaveTangentWeight": 0.0
              }
            ],
            "DefaultValue": 3.4028235E+38,
            "PreInfinityExtrap": "RCCE_Constant",
            "PostInfinityExtrap": "RCCE_Constant"
          },
          "Name": {
            "DisplayName": "FootPlants"
          },
          "CurveTypeFlags": 4
        },
        {
          "FloatCurve": {
            "Keys": [
              {
                "InterpMode": "RCIM_Linear",
                "TangentMode": "RCTM_Auto",
                "TangentWeightMode": "RCTWM_WeightedNone",
                "Time": 0.0,
                "Value": 4.6552815,
                "ArriveTangent": 3.6792223,
                "ArriveTangentWeight": 0.0,
                "LeaveTangent": 2.6333182,
                "LeaveTangentWeight": 0.0
              },
              {
                "InterpMode": "RCIM_Linear",
                "TangentMode": "RCTM_Auto",
                "TangentWeightMode": "RCTWM_WeightedNone",
                "Time": 0.033333335,
                "Value": 3.6792223,
                "ArriveTangent": 2.6333182,
                "ArriveTangentWeight": 0.0,
                "LeaveTangent": 2.1501215,
                "LeaveTangentWeight": 0.0
              },
              {
                "InterpMode": "RCIM_Linear",
                "TangentMode": "RCTM_Auto",
                "TangentWeightMode": "RCTWM_WeightedNone",
                "Time": 0.06666667,
                "Value": 2.6333182,
                "ArriveTangent": 2.1501215,
                "ArriveTangentWeight": 0.0,
                "LeaveTangent": 1.754159,
                "LeaveTangentWeight": 0.0
              },
              {
                "InterpMode": "RCIM_Linear",
                "TangentMode": "RCTM_Auto",
                "TangentWeightMode": "RCTWM_WeightedNone",
                "Time": 0.10000001,
                "Value": 2.1501215,
                "ArriveTangent": 1.754159,
                "ArriveTangentWeight": 0.0,
                "LeaveTangent": 1.4243629,
                "LeaveTangentWeight": 0.0
              },
              {
                "InterpMode": "RCIM_Linear",
                "TangentMode": "RCTM_Auto",
                "TangentWeightMode": "RCTWM_WeightedNone",
                "Time": 0.13333334,
                "Value": 1.754159,
                "ArriveTangent": 1.4243629,
                "ArriveTangentWeight": 0.0,
                "LeaveTangent": 1.4862405,
                "LeaveTangentWeight": 0.0
              },
              {
                "InterpMode": "RCIM_Linear",
                "TangentMode": "RCTM_Auto",
                "TangentWeightMode": "RCTWM_WeightedNone",
                "Time": 0.16666667,
                "Value": 1.4243629,
                "ArriveTangent": 1.4862405,
                "ArriveTangentWeight": 0.0,
                "LeaveTangent": 2.0081186,
                "LeaveTangentWeight": 0.0
              },
              {
                "InterpMode": "RCIM_Linear",
                "TangentMode": "RCTM_Auto",
                "TangentWeightMode": "RCTWM_WeightedNone",
                "Time": 0.20000002,
                "Value": 1.4862405,
                "ArriveTangent": 2.0081186,
                "ArriveTangentWeight": 0.0,
                "LeaveTangent": 2.5459213,
                "LeaveTangentWeight": 0.0
              },
              {
                "InterpMode": "RCIM_Linear",
                "TangentMode": "RCTM_Auto",
                "TangentWeightMode": "RCTWM_WeightedNone",
                "Time": 0.23333335,
                "Value": 2.0081186,
                "ArriveTangent": 2.5459213,
                "ArriveTangentWeight": 0.0,
                "LeaveTangent": 3.559482,
                "LeaveTangentWeight": 0.0
              },
              {
                "InterpMode": "RCIM_Linear",
                "TangentMode": "RCTM_Auto",
                "TangentWeightMode": "RCTWM_WeightedNone",
                "Time": 0.26666668,
                "Value": 2.5459213,
                "ArriveTangent": 3.559482,
                "ArriveTangentWeight": 0.0,
                "LeaveTangent": 4.452743,
                "LeaveTangentWeight": 0.0
              },
              {
                "InterpMode": "RCIM_Linear",
                "TangentMode": "RCTM_Auto",
                "TangentWeightMode": "RCTWM_WeightedNone",
                "Time": 0.3,
                "Value": 3.559482,
                "ArriveTangent": 4.452743,
                "ArriveTangentWeight": 0.0,
                "LeaveTangent": 5.0626297,
                "LeaveTangentWeight": 0.0
              },
              {
                "InterpMode": "RCIM_Linear",
                "TangentMode": "RCTM_Auto",
                "TangentWeightMode": "RCTWM_WeightedNone",
                "Time": 0.33333334,
                "Value": 4.452743,
                "ArriveTangent": 5.0626297,
                "ArriveTangentWeight": 0.0,
                "LeaveTangent": 5.7300467,
                "LeaveTangentWeight": 0.0
              },
              {
                "InterpMode": "RCIM_Linear",
                "TangentMode": "RCTM_Auto",
                "TangentWeightMode": "RCTWM_WeightedNone",
                "Time": 0.36666667,
                "Value": 5.0626297,
                "ArriveTangent": 5.7300467,
                "ArriveTangentWeight": 0.0,
                "LeaveTangent": 5.8494253,
                "LeaveTangentWeight": 0.0
              },
              {
                "InterpMode": "RCIM_Linear",
                "TangentMode": "RCTM_Auto",
                "TangentWeightMode": "RCTWM_WeightedNone",
                "Time": 0.40000004,
                "Value": 5.7300467,
                "ArriveTangent": 5.8494253,
                "ArriveTangentWeight": 0.0,
                "LeaveTangent": 6.2136674,
                "LeaveTangentWeight": 0.0
              },
              {
                "InterpMode": "RCIM_Linear",
                "TangentMode": "RCTM_Auto",
                "TangentWeightMode": "RCTWM_WeightedNone",
                "Time": 0.43333337,
                "Value": 5.8494253,
                "ArriveTangent": 6.2136674,
                "ArriveTangentWeight": 0.0,
                "LeaveTangent": 7.331113,
                "LeaveTangentWeight": 0.0
              },
              {
                "InterpMode": "RCIM_Linear",
                "TangentMode": "RCTM_Auto",
                "TangentWeightMode": "RCTWM_WeightedNone",
                "Time": 0.4666667,
                "Value": 6.2136674,
                "ArriveTangent": 7.331113,
                "ArriveTangentWeight": 0.0,
                "LeaveTangent": 7.468028,
                "LeaveTangentWeight": 0.0
              },
              {
                "InterpMode": "RCIM_Linear",
                "TangentMode": "RCTM_Auto",
                "TangentWeightMode": "RCTWM_WeightedNone",
                "Time": 0.5,
                "Value": 7.331113,
                "ArriveTangent": 7.468028,
                "ArriveTangentWeight": 0.0,
                "LeaveTangent": 7.1379466,
                "LeaveTangentWeight": 0.0
              },
              {
                "InterpMode": "RCIM_Linear",
                "TangentMode": "RCTM_Auto",
                "TangentWeightMode": "RCTWM_WeightedNone",
                "Time": 0.53333336,
                "Value": 7.468028,
                "ArriveTangent": 7.1379466,
                "ArriveTangentWeight": 0.0,
                "LeaveTangent": 5.9670343,
                "LeaveTangentWeight": 0.0
              },
              {
                "InterpMode": "RCIM_Linear",
                "TangentMode": "RCTM_Auto",
                "TangentWeightMode": "RCTWM_WeightedNone",
                "Time": 0.5666667,
                "Value": 7.1379466,
                "ArriveTangent": 5.9670343,
                "ArriveTangentWeight": 0.0,
                "LeaveTangent": 4.265025,
                "LeaveTangentWeight": 0.0
              },
              {
                "InterpMode": "RCIM_Linear",
                "TangentMode": "RCTM_Auto",
                "TangentWeightMode": "RCTWM_WeightedNone",
                "Time": 0.6,
                "Value": 5.9670343,
                "ArriveTangent": 4.265025,
                "ArriveTangentWeight": 0.0,
                "LeaveTangent": 2.8430052,
                "LeaveTangentWeight": 0.0
              },
              {
                "InterpMode": "RCIM_Linear",
                "TangentMode": "RCTM_Auto",
                "TangentWeightMode": "RCTWM_WeightedNone",
                "Time": 0.6333334,
                "Value": 4.265025,
                "ArriveTangent": 2.8430052,
                "ArriveTangentWeight": 0.0,
                "LeaveTangent": 1.8527569,
                "LeaveTangentWeight": 0.0
              },
              {
                "InterpMode": "RCIM_Linear",
                "TangentMode": "RCTM_Auto",
                "TangentWeightMode": "RCTWM_WeightedNone",
                "Time": 0.6666667,
                "Value": 2.8430052,
                "ArriveTangent": 1.8527569,
                "ArriveTangentWeight": 0.0,
                "LeaveTangent": 1.5913621,
                "LeaveTangentWeight": 0.0
              },
              {
                "InterpMode": "RCIM_Linear",
                "TangentMode": "RCTM_Auto",
                "TangentWeightMode": "RCTWM_WeightedNone",
                "Time": 0.70000005,
                "Value": 1.8527569,
                "ArriveTangent": 1.5913621,
                "ArriveTangentWeight": 0.0,
                "LeaveTangent": 1.7331103,
                "LeaveTangentWeight": 0.0
              },
              {
                "InterpMode": "RCIM_Linear",
                "TangentMode": "RCTM_Auto",
                "TangentWeightMode": "RCTWM_WeightedNone",
                "Time": 0.73333335,
                "Value": 1.5913621,
                "ArriveTangent": 1.7331103,
                "ArriveTangentWeight": 0.0,
                "LeaveTangent": 2.2672994,
                "LeaveTangentWeight": 0.0
              },
              {
                "InterpMode": "RCIM_Linear",
                "TangentMode": "RCTM_Auto",
                "TangentWeightMode": "RCTWM_WeightedNone",
                "Time": 0.7666667,
                "Value": 1.7331103,
                "ArriveTangent": 2.2672994,
                "ArriveTangentWeight": 0.0,
                "LeaveTangent": 2.3276463,
                "LeaveTangentWeight": 0.0
              },
              {
                "InterpMode": "RCIM_Linear",
                "TangentMode": "RCTM_Auto",
                "TangentWeightMode": "RCTWM_WeightedNone",
                "Time": 0.8000001,
                "Value": 2.2672994,
                "ArriveTangent": 2.3276463,
                "ArriveTangentWeight": 0.0,
                "LeaveTangent": 1.5647947,
                "LeaveTangentWeight": 0.0
              },
              {
                "InterpMode": "RCIM_Linear",
                "TangentMode": "RCTM_Auto",
                "TangentWeightMode": "RCTWM_WeightedNone",
                "Time": 0.8333334,
                "Value": 2.3276463,
                "ArriveTangent": 1.5647947,
                "ArriveTangentWeight": 0.0,
                "LeaveTangent": 0.6857242,
                "LeaveTangentWeight": 0.0
              },
              {
                "InterpMode": "RCIM_Linear",
                "TangentMode": "RCTM_Auto",
                "TangentWeightMode": "RCTWM_WeightedNone",
                "Time": 0.86666673,
                "Value": 1.5647947,
                "ArriveTangent": 0.6857242,
                "ArriveTangentWeight": 0.0,
                "LeaveTangent": 0.9497565,
                "LeaveTangentWeight": 0.0
              },
              {
                "InterpMode": "RCIM_Linear",
                "TangentMode": "RCTM_Auto",
                "TangentWeightMode": "RCTWM_WeightedNone",
                "Time": 0.90000004,
                "Value": 0.6857242,
                "ArriveTangent": 0.9497565,
                "ArriveTangentWeight": 0.0,
                "LeaveTangent": 1.5271577,
                "LeaveTangentWeight": 0.0
              },
              {
                "InterpMode": "RCIM_Linear",
                "TangentMode": "RCTM_Auto",
                "TangentWeightMode": "RCTWM_WeightedNone",
                "Time": 0.9333334,
                "Value": 0.9497565,
                "ArriveTangent": 1.5271577,
                "ArriveTangentWeight": 0.0,
                "LeaveTangent": 1.8467396,
                "LeaveTangentWeight": 0.0
              },
              {
                "InterpMode": "RCIM_Linear",
                "TangentMode": "RCTM_Auto",
                "TangentWeightMode": "RCTWM_WeightedNone",
                "Time": 0.9666667,
                "Value": 1.5271577,
                "ArriveTangent": 1.8467396,
                "ArriveTangentWeight": 0.0,
                "LeaveTangent": 1.8451201,
                "LeaveTangentWeight": 0.0
              },
              {
                "InterpMode": "RCIM_Linear",
                "TangentMode": "RCTM_Auto",
                "TangentWeightMode": "RCTWM_WeightedNone",
                "Time": 1.0,
                "Value": 1.8467396,
                "ArriveTangent": 1.8451201,
                "ArriveTangentWeight": 0.0,
                "LeaveTangent": 1.6338913,
                "LeaveTangentWeight": 0.0
              },
              {
                "InterpMode": "RCIM_Linear",
                "TangentMode": "RCTM_Auto",
                "TangentWeightMode": "RCTWM_WeightedNone",
                "Time": 1.0333334,
                "Value": 1.8451201,
                "ArriveTangent": 1.6338913,
                "ArriveTangentWeight": 0.0,
                "LeaveTangent": 1.3918563,
                "LeaveTangentWeight": 0.0
              },
              {
                "InterpMode": "RCIM_Linear",
                "TangentMode": "RCTM_Auto",
                "TangentWeightMode": "RCTWM_WeightedNone",
                "Time": 1.0666667,
                "Value": 1.6338913,
                "ArriveTangent": 1.3918563,
                "ArriveTangentWeight": 0.0,
                "LeaveTangent": 1.0612751,
                "LeaveTangentWeight": 0.0
              },
              {
                "InterpMode": "RCIM_Linear",
                "TangentMode": "RCTM_Auto",
                "TangentWeightMode": "RCTWM_WeightedNone",
                "Time": 1.1,
                "Value": 1.3918563,
                "ArriveTangent": 1.0612751,
                "ArriveTangentWeight": 0.0,
                "LeaveTangent": 1.1299893,
                "LeaveTangentWeight": 0.0
              },
              {
                "InterpMode": "RCIM_Linear",
                "TangentMode": "RCTM_Auto",
                "TangentWeightMode": "RCTWM_WeightedNone",
                "Time": 1.1666667,
                "Value": 1.0612751,
                "ArriveTangent": 1.1299893,
                "ArriveTangentWeight": 0.0,
                "LeaveTangent": 1.3427979,
                "LeaveTangentWeight": 0.0
              },
              {
                "InterpMode": "RCIM_Linear",
                "TangentMode": "RCTM_Auto",
                "TangentWeightMode": "RCTWM_WeightedNone",
                "Time": 1.2,
                "Value": 1.1299893,
                "ArriveTangent": 1.3427979,
                "ArriveTangentWeight": 0.0,
                "LeaveTangent": 1.4294418,
                "LeaveTangentWeight": 0.0
              },
              {
                "InterpMode": "RCIM_Linear",
                "TangentMode": "RCTM_Auto",
                "TangentWeightMode": "RCTWM_WeightedNone",
                "Time": 1.2333333,
                "Value": 1.3427979,
                "ArriveTangent": 1.4294418,
                "ArriveTangentWeight": 0.0,
                "LeaveTangent": 1.3711274,
                "LeaveTangentWeight": 0.0
              },
              {
                "InterpMode": "RCIM_Linear",
                "TangentMode": "RCTM_Auto",
                "TangentWeightMode": "RCTWM_WeightedNone",
                "Time": 1.2666668,
                "Value": 1.4294418,
                "ArriveTangent": 1.3711274,
                "ArriveTangentWeight": 0.0,
                "LeaveTangent": 1.0623747,
                "LeaveTangentWeight": 0.0
              },
              {
                "InterpMode": "RCIM_Linear",
                "TangentMode": "RCTM_Auto",
                "TangentWeightMode": "RCTWM_WeightedNone",
                "Time": 1.3000001,
                "Value": 1.3711274,
                "ArriveTangent": 1.0623747,
                "ArriveTangentWeight": 0.0,
                "LeaveTangent": 0.90180975,
                "LeaveTangentWeight": 0.0
              },
              {
                "InterpMode": "RCIM_Linear",
                "TangentMode": "RCTM_Auto",
                "TangentWeightMode": "RCTWM_WeightedNone",
                "Time": 1.3333334,
                "Value": 1.0623747,
                "ArriveTangent": 0.90180975,
                "ArriveTangentWeight": 0.0,
                "LeaveTangent": 1.2218751,
                "LeaveTangentWeight": 0.0
              },
              {
                "InterpMode": "RCIM_Linear",
                "TangentMode": "RCTM_Auto",
                "TangentWeightMode": "RCTWM_WeightedNone",
                "Time": 1.3666668,
                "Value": 0.90180975,
                "ArriveTangent": 1.2218751,
                "ArriveTangentWeight": 0.0,
                "LeaveTangent": 1.6581839,
                "LeaveTangentWeight": 0.0
              },
              {
                "InterpMode": "RCIM_Linear",
                "TangentMode": "RCTM_Auto",
                "TangentWeightMode": "RCTWM_WeightedNone",
                "Time": 1.4000001,
                "Value": 1.2218751,
                "ArriveTangent": 1.6581839,
                "ArriveTangentWeight": 0.0,
                "LeaveTangent": 2.289533,
                "LeaveTangentWeight": 0.0
              },
              {
                "InterpMode": "RCIM_Linear",
                "TangentMode": "RCTM_Auto",
                "TangentWeightMode": "RCTWM_WeightedNone",
                "Time": 1.4333334,
                "Value": 1.6581839,
                "ArriveTangent": 2.289533,
                "ArriveTangentWeight": 0.0,
                "LeaveTangent": 3.0053198,
                "LeaveTangentWeight": 0.0
              },
              {
                "InterpMode": "RCIM_Linear",
                "TangentMode": "RCTM_Auto",
                "TangentWeightMode": "RCTWM_WeightedNone",
                "Time": 1.4666667,
                "Value": 2.289533,
                "ArriveTangent": 3.0053198,
                "ArriveTangentWeight": 0.0,
                "LeaveTangent": 3.3119314,
                "LeaveTangentWeight": 0.0
              },
              {
                "InterpMode": "RCIM_Linear",
                "TangentMode": "RCTM_Auto",
                "TangentWeightMode": "RCTWM_WeightedNone",
                "Time": 1.5000001,
                "Value": 3.0053198,
                "ArriveTangent": 3.3119314,
                "ArriveTangentWeight": 0.0,
                "LeaveTangent": 3.4190867,
                "LeaveTangentWeight": 0.0
              },
              {
                "InterpMode": "RCIM_Linear",
                "TangentMode": "RCTM_Auto",
                "TangentWeightMode": "RCTWM_WeightedNone",
                "Time": 1.5333334,
                "Value": 3.3119314,
                "ArriveTangent": 3.4190867,
                "ArriveTangentWeight": 0.0,
                "LeaveTangent": 3.2724497,
                "LeaveTangentWeight": 0.0
              },
              {
                "InterpMode": "RCIM_Linear",
                "TangentMode": "RCTM_Auto",
                "TangentWeightMode": "RCTWM_WeightedNone",
                "Time": 1.5666667,
                "Value": 3.4190867,
                "ArriveTangent": 3.2724497,
                "ArriveTangentWeight": 0.0,
                "LeaveTangent": 3.1416392,
                "LeaveTangentWeight": 0.0
              },
              {
                "InterpMode": "RCIM_Linear",
                "TangentMode": "RCTM_Auto",
                "TangentWeightMode": "RCTWM_WeightedNone",
                "Time": 1.6000001,
                "Value": 3.2724497,
                "ArriveTangent": 3.1416392,
                "ArriveTangentWeight": 0.0,
                "LeaveTangent": 2.549931,
                "LeaveTangentWeight": 0.0
              },
              {
                "InterpMode": "RCIM_Linear",
                "TangentMode": "RCTM_Auto",
                "TangentWeightMode": "RCTWM_WeightedNone",
                "Time": 1.6333334,
                "Value": 3.1416392,
                "ArriveTangent": 2.549931,
                "ArriveTangentWeight": 0.0,
                "LeaveTangent": 1.9231577,
                "LeaveTangentWeight": 0.0
              },
              {
                "InterpMode": "RCIM_Linear",
                "TangentMode": "RCTM_Auto",
                "TangentWeightMode": "RCTWM_WeightedNone",
                "Time": 1.6666667,
                "Value": 2.549931,
                "ArriveTangent": 1.9231577,
                "ArriveTangentWeight": 0.0,
                "LeaveTangent": 1.7989388,
                "LeaveTangentWeight": 0.0
              },
              {
                "InterpMode": "RCIM_Linear",
                "TangentMode": "RCTM_Auto",
                "TangentWeightMode": "RCTWM_WeightedNone",
                "Time": 1.7,
                "Value": 1.9231577,
                "ArriveTangent": 1.7989388,
                "ArriveTangentWeight": 0.0,
                "LeaveTangent": 2.5455165,
                "LeaveTangentWeight": 0.0
              },
              {
                "InterpMode": "RCIM_Linear",
                "TangentMode": "RCTM_Auto",
                "TangentWeightMode": "RCTWM_WeightedNone",
                "Time": 1.7333335,
                "Value": 1.7989388,
                "ArriveTangent": 2.5455165,
                "ArriveTangentWeight": 0.0,
                "LeaveTangent": 2.9433665,
                "LeaveTangentWeight": 0.0
              },
              {
                "InterpMode": "RCIM_Linear",
                "TangentMode": "RCTM_Auto",
                "TangentWeightMode": "RCTWM_WeightedNone",
                "Time": 1.7666668,
                "Value": 2.5455165,
                "ArriveTangent": 2.9433665,
                "ArriveTangentWeight": 0.0,
                "LeaveTangent": 3.3309832,
                "LeaveTangentWeight": 0.0
              },
              {
                "InterpMode": "RCIM_Linear",
                "TangentMode": "RCTM_Auto",
                "TangentWeightMode": "RCTWM_WeightedNone",
                "Time": 1.8000001,
                "Value": 2.9433665,
                "ArriveTangent": 3.3309832,
                "ArriveTangentWeight": 0.0,
                "LeaveTangent": 3.6253996,
                "LeaveTangentWeight": 0.0
              },
              {
                "InterpMode": "RCIM_Linear",
                "TangentMode": "RCTM_Auto",
                "TangentWeightMode": "RCTWM_WeightedNone",
                "Time": 1.8333334,
                "Value": 3.3309832,
                "ArriveTangent": 3.6253996,
                "ArriveTangentWeight": 0.0,
                "LeaveTangent": 3.7958896,
                "LeaveTangentWeight": 0.0
              },
              {
                "InterpMode": "RCIM_Linear",
                "TangentMode": "RCTM_Auto",
                "TangentWeightMode": "RCTWM_WeightedNone",
                "Time": 1.8666668,
                "Value": 3.6253996,
                "ArriveTangent": 3.7958896,
                "ArriveTangentWeight": 0.0,
                "LeaveTangent": 4.1958575,
                "LeaveTangentWeight": 0.0
              },
              {
                "InterpMode": "RCIM_Linear",
                "TangentMode": "RCTM_Auto",
                "TangentWeightMode": "RCTWM_WeightedNone",
                "Time": 1.9000001,
                "Value": 3.7958896,
                "ArriveTangent": 4.1958575,
                "ArriveTangentWeight": 0.0,
                "LeaveTangent": 4.2904835,
                "LeaveTangentWeight": 0.0
              },
              {
                "InterpMode": "RCIM_Linear",
                "TangentMode": "RCTM_Auto",
                "TangentWeightMode": "RCTWM_WeightedNone",
                "Time": 1.9333334,
                "Value": 4.1958575,
                "ArriveTangent": 4.2904835,
                "ArriveTangentWeight": 0.0,
                "LeaveTangent": 4.3328624,
                "LeaveTangentWeight": 0.0
              },
              {
                "InterpMode": "RCIM_Linear",
                "TangentMode": "RCTM_Auto",
                "TangentWeightMode": "RCTWM_WeightedNone",
                "Time": 1.9666668,
                "Value": 4.2904835,
                "ArriveTangent": 4.3328624,
                "ArriveTangentWeight": 0.0,
                "LeaveTangent": 4.3821135,
                "LeaveTangentWeight": 0.0
              },
              {
                "InterpMode": "RCIM_Linear",
                "TangentMode": "RCTM_Auto",
                "TangentWeightMode": "RCTWM_WeightedNone",
                "Time": 2.0,
                "Value": 4.3328624,
                "ArriveTangent": 4.3821135,
                "ArriveTangentWeight": 0.0,
                "LeaveTangent": 4.3764052,
                "LeaveTangentWeight": 0.0
              },
              {
                "InterpMode": "RCIM_Linear",
                "TangentMode": "RCTM_Auto",
                "TangentWeightMode": "RCTWM_WeightedNone",
                "Time": 2.0333335,
                "Value": 4.3821135,
                "ArriveTangent": 4.3764052,
                "ArriveTangentWeight": 0.0,
                "LeaveTangent": 4.3729787,
                "LeaveTangentWeight": 0.0
              },
              {
                "InterpMode": "RCIM_Linear",
                "TangentMode": "RCTM_Auto",
                "TangentWeightMode": "RCTWM_WeightedNone",
                "Time": 2.0666668,
                "Value": 4.3764052,
                "ArriveTangent": 4.3729787,
                "ArriveTangentWeight": 0.0,
                "LeaveTangent": 4.6041656,
                "LeaveTangentWeight": 0.0
              },
              {
                "InterpMode": "RCIM_Linear",
                "TangentMode": "RCTM_Auto",
                "TangentWeightMode": "RCTWM_WeightedNone",
                "Time": 2.1000001,
                "Value": 4.3729787,
                "ArriveTangent": 4.6041656,
                "ArriveTangentWeight": 0.0,
                "LeaveTangent": 4.8227954,
                "LeaveTangentWeight": 0.0
              },
              {
                "InterpMode": "RCIM_Linear",
                "TangentMode": "RCTM_Auto",
                "TangentWeightMode": "RCTWM_WeightedNone",
                "Time": 2.1333334,
                "Value": 4.6041656,
                "ArriveTangent": 4.8227954,
                "ArriveTangentWeight": 0.0,
                "LeaveTangent": 4.6821804,
                "LeaveTangentWeight": 0.0
              },
              {
                "InterpMode": "RCIM_Linear",
                "TangentMode": "RCTM_Auto",
                "TangentWeightMode": "RCTWM_WeightedNone",
                "Time": 2.1666667,
                "Value": 4.8227954,
                "ArriveTangent": 4.6821804,
                "ArriveTangentWeight": 0.0,
                "LeaveTangent": 4.404109,
                "LeaveTangentWeight": 0.0
              },
              {
                "InterpMode": "RCIM_Linear",
                "TangentMode": "RCTM_Auto",
                "TangentWeightMode": "RCTWM_WeightedNone",
                "Time": 2.2,
                "Value": 4.6821804,
                "ArriveTangent": 4.404109,
                "ArriveTangentWeight": 0.0,
                "LeaveTangent": 3.9638941,
                "LeaveTangentWeight": 0.0
              },
              {
                "InterpMode": "RCIM_Linear",
                "TangentMode": "RCTM_Auto",
                "TangentWeightMode": "RCTWM_WeightedNone",
                "Time": 2.2333333,
                "Value": 4.404109,
                "ArriveTangent": 3.9638941,
                "ArriveTangentWeight": 0.0,
                "LeaveTangent": 3.399937,
                "LeaveTangentWeight": 0.0
              },
              {
                "InterpMode": "RCIM_Linear",
                "TangentMode": "RCTM_Auto",
                "TangentWeightMode": "RCTWM_WeightedNone",
                "Time": 2.266667,
                "Value": 3.9638941,
                "ArriveTangent": 3.399937,
                "ArriveTangentWeight": 0.0,
                "LeaveTangent": 2.933188,
                "LeaveTangentWeight": 0.0
              },
              {
                "InterpMode": "RCIM_Linear",
                "TangentMode": "RCTM_Auto",
                "TangentWeightMode": "RCTWM_WeightedNone",
                "Time": 2.3000002,
                "Value": 3.399937,
                "ArriveTangent": 2.933188,
                "ArriveTangentWeight": 0.0,
                "LeaveTangent": 2.566373,
                "LeaveTangentWeight": 0.0
              },
              {
                "InterpMode": "RCIM_Linear",
                "TangentMode": "RCTM_Auto",
                "TangentWeightMode": "RCTWM_WeightedNone",
                "Time": 2.3333335,
                "Value": 2.933188,
                "ArriveTangent": 2.566373,
                "ArriveTangentWeight": 0.0,
                "LeaveTangent": 2.0885034,
                "LeaveTangentWeight": 0.0
              },
              {
                "InterpMode": "RCIM_Linear",
                "TangentMode": "RCTM_Auto",
                "TangentWeightMode": "RCTWM_WeightedNone",
                "Time": 2.3666668,
                "Value": 2.566373,
                "ArriveTangent": 2.0885034,
                "ArriveTangentWeight": 0.0,
                "LeaveTangent": 1.8345039,
                "LeaveTangentWeight": 0.0
              },
              {
                "InterpMode": "RCIM_Linear",
                "TangentMode": "RCTM_Auto",
                "TangentWeightMode": "RCTWM_WeightedNone",
                "Time": 2.4,
                "Value": 2.0885034,
                "ArriveTangent": 1.8345039,
                "ArriveTangentWeight": 0.0,
                "LeaveTangent": 1.4515318,
                "LeaveTangentWeight": 0.0
              },
              {
                "InterpMode": "RCIM_Linear",
                "TangentMode": "RCTM_Auto",
                "TangentWeightMode": "RCTWM_WeightedNone",
                "Time": 2.4333334,
                "Value": 1.8345039,
                "ArriveTangent": 1.4515318,
                "ArriveTangentWeight": 0.0,
                "LeaveTangent": 1.2701681,
                "LeaveTangentWeight": 0.0
              },
              {
                "InterpMode": "RCIM_Linear",
                "TangentMode": "RCTM_Auto",
                "TangentWeightMode": "RCTWM_WeightedNone",
                "Time": 2.4666667,
                "Value": 1.4515318,
                "ArriveTangent": 1.2701681,
                "ArriveTangentWeight": 0.0,
                "LeaveTangent": 1.3079537,
                "LeaveTangentWeight": 0.0
              },
              {
                "InterpMode": "RCIM_Linear",
                "TangentMode": "RCTM_Auto",
                "TangentWeightMode": "RCTWM_WeightedNone",
                "Time": 2.5000002,
                "Value": 1.2701681,
                "ArriveTangent": 1.3079537,
                "ArriveTangentWeight": 0.0,
                "LeaveTangent": 1.3531518,
                "LeaveTangentWeight": 0.0
              },
              {
                "InterpMode": "RCIM_Linear",
                "TangentMode": "RCTM_Auto",
                "TangentWeightMode": "RCTWM_WeightedNone",
                "Time": 2.5333335,
                "Value": 1.3079537,
                "ArriveTangent": 1.3531518,
                "ArriveTangentWeight": 0.0,
                "LeaveTangent": 1.5007734,
                "LeaveTangentWeight": 0.0
              },
              {
                "InterpMode": "RCIM_Linear",
                "TangentMode": "RCTM_Auto",
                "TangentWeightMode": "RCTWM_WeightedNone",
                "Time": 2.5666668,
                "Value": 1.3531518,
                "ArriveTangent": 1.5007734,
                "ArriveTangentWeight": 0.0,
                "LeaveTangent": 1.7009436,
                "LeaveTangentWeight": 0.0
              },
              {
                "InterpMode": "RCIM_Linear",
                "TangentMode": "RCTM_Auto",
                "TangentWeightMode": "RCTWM_WeightedNone",
                "Time": 2.6000001,
                "Value": 1.5007734,
                "ArriveTangent": 1.7009436,
                "ArriveTangentWeight": 0.0,
                "LeaveTangent": 1.7077285,
                "LeaveTangentWeight": 0.0
              },
              {
                "InterpMode": "RCIM_Linear",
                "TangentMode": "RCTM_Auto",
                "TangentWeightMode": "RCTWM_WeightedNone",
                "Time": 2.6333334,
                "Value": 1.7009436,
                "ArriveTangent": 1.7077285,
                "ArriveTangentWeight": 0.0,
                "LeaveTangent": 1.6485702,
                "LeaveTangentWeight": 0.0
              },
              {
                "InterpMode": "RCIM_Linear",
                "TangentMode": "RCTM_Auto",
                "TangentWeightMode": "RCTWM_WeightedNone",
                "Time": 2.6666667,
                "Value": 1.7077285,
                "ArriveTangent": 1.6485702,
                "ArriveTangentWeight": 0.0,
                "LeaveTangent": 1.5144914,
                "LeaveTangentWeight": 0.0
              },
              {
                "InterpMode": "RCIM_Linear",
                "TangentMode": "RCTM_Auto",
                "TangentWeightMode": "RCTWM_WeightedNone",
                "Time": 2.7,
                "Value": 1.6485702,
                "ArriveTangent": 1.5144914,
                "ArriveTangentWeight": 0.0,
                "LeaveTangent": 1.5385729,
                "LeaveTangentWeight": 0.0
              },
              {
                "InterpMode": "RCIM_Linear",
                "TangentMode": "RCTM_Auto",
                "TangentWeightMode": "RCTWM_WeightedNone",
                "Time": 2.7333336,
                "Value": 1.5144914,
                "ArriveTangent": 1.5385729,
                "ArriveTangentWeight": 0.0,
                "LeaveTangent": 1.8410301,
                "LeaveTangentWeight": 0.0
              },
              {
                "InterpMode": "RCIM_Linear",
                "TangentMode": "RCTM_Auto",
                "TangentWeightMode": "RCTWM_WeightedNone",
                "Time": 2.766667,
                "Value": 1.5385729,
                "ArriveTangent": 1.8410301,
                "ArriveTangentWeight": 0.0,
                "LeaveTangent": 2.0903492,
                "LeaveTangentWeight": 0.0
              },
              {
                "InterpMode": "RCIM_Linear",
                "TangentMode": "RCTM_Auto",
                "TangentWeightMode": "RCTWM_WeightedNone",
                "Time": 2.8000002,
                "Value": 1.8410301,
                "ArriveTangent": 2.0903492,
                "ArriveTangentWeight": 0.0,
                "LeaveTangent": 2.441358,
                "LeaveTangentWeight": 0.0
              },
              {
                "InterpMode": "RCIM_Linear",
                "TangentMode": "RCTM_Auto",
                "TangentWeightMode": "RCTWM_WeightedNone",
                "Time": 2.8333335,
                "Value": 2.0903492,
                "ArriveTangent": 2.441358,
                "ArriveTangentWeight": 0.0,
                "LeaveTangent": 2.888668,
                "LeaveTangentWeight": 0.0
              },
              {
                "InterpMode": "RCIM_Linear",
                "TangentMode": "RCTM_Auto",
                "TangentWeightMode": "RCTWM_WeightedNone",
                "Time": 2.8666668,
                "Value": 2.441358,
                "ArriveTangent": 2.888668,
                "ArriveTangentWeight": 0.0,
                "LeaveTangent": 3.3195794,
                "LeaveTangentWeight": 0.0
              },
              {
                "InterpMode": "RCIM_Linear",
                "TangentMode": "RCTM_Auto",
                "TangentWeightMode": "RCTWM_WeightedNone",
                "Time": 2.9,
                "Value": 2.888668,
                "ArriveTangent": 3.3195794,
                "ArriveTangentWeight": 0.0,
                "LeaveTangent": 3.67692,
                "LeaveTangentWeight": 0.0
              },
              {
                "InterpMode": "RCIM_Linear",
                "TangentMode": "RCTM_Auto",
                "TangentWeightMode": "RCTWM_WeightedNone",
                "Time": 2.9333334,
                "Value": 3.3195794,
                "ArriveTangent": 3.67692,
                "ArriveTangentWeight": 0.0,
                "LeaveTangent": 3.920867,
                "LeaveTangentWeight": 0.0
              },
              {
                "InterpMode": "RCIM_Linear",
                "TangentMode": "RCTM_Auto",
                "TangentWeightMode": "RCTWM_WeightedNone",
                "Time": 2.966667,
                "Value": 3.67692,
                "ArriveTangent": 3.920867,
                "ArriveTangentWeight": 0.0,
                "LeaveTangent": 4.0381937,
                "LeaveTangentWeight": 0.0
              },
              {
                "InterpMode": "RCIM_Linear",
                "TangentMode": "RCTM_Auto",
                "TangentWeightMode": "RCTWM_WeightedNone",
                "Time": 3.0000002,
                "Value": 3.920867,
                "ArriveTangent": 4.0381937,
                "ArriveTangentWeight": 0.0,
                "LeaveTangent": 4.2727404,
                "LeaveTangentWeight": 0.0
              },
              {
                "InterpMode": "RCIM_Linear",
                "TangentMode": "RCTM_Auto",
                "TangentWeightMode": "RCTWM_WeightedNone",
                "Time": 3.0333335,
                "Value": 4.0381937,
                "ArriveTangent": 4.2727404,
                "ArriveTangentWeight": 0.0,
                "LeaveTangent": 4.5170155,
                "LeaveTangentWeight": 0.0
              },
              {
                "InterpMode": "RCIM_Linear",
                "TangentMode": "RCTM_Auto",
                "TangentWeightMode": "RCTWM_WeightedNone",
                "Time": 3.0666668,
                "Value": 4.2727404,
                "ArriveTangent": 4.5170155,
                "ArriveTangentWeight": 0.0,
                "LeaveTangent": 4.7128906,
                "LeaveTangentWeight": 0.0
              },
              {
                "InterpMode": "RCIM_Linear",
                "TangentMode": "RCTM_Auto",
                "TangentWeightMode": "RCTWM_WeightedNone",
                "Time": 3.1000001,
                "Value": 4.5170155,
                "ArriveTangent": 4.7128906,
                "ArriveTangentWeight": 0.0,
                "LeaveTangent": 4.8461714,
                "LeaveTangentWeight": 0.0
              },
              {
                "InterpMode": "RCIM_Linear",
                "TangentMode": "RCTM_Auto",
                "TangentWeightMode": "RCTWM_WeightedNone",
                "Time": 3.1333334,
                "Value": 4.7128906,
                "ArriveTangent": 4.8461714,
                "ArriveTangentWeight": 0.0,
                "LeaveTangent": 4.8247995,
                "LeaveTangentWeight": 0.0
              },
              {
                "InterpMode": "RCIM_Linear",
                "TangentMode": "RCTM_Auto",
                "TangentWeightMode": "RCTWM_WeightedNone",
                "Time": 3.1666667,
                "Value": 4.8461714,
                "ArriveTangent": 4.8247995,
                "ArriveTangentWeight": 0.0,
                "LeaveTangent": 4.83386,
                "LeaveTangentWeight": 0.0
              },
              {
                "InterpMode": "RCIM_Linear",
                "TangentMode": "RCTM_Auto",
                "TangentWeightMode": "RCTWM_WeightedNone",
                "Time": 3.2000003,
                "Value": 4.8247995,
                "ArriveTangent": 4.83386,
                "ArriveTangentWeight": 0.0,
                "LeaveTangent": 4.451988,
                "LeaveTangentWeight": 0.0
              },
              {
                "InterpMode": "RCIM_Linear",
                "TangentMode": "RCTM_Auto",
                "TangentWeightMode": "RCTWM_WeightedNone",
                "Time": 3.2333336,
                "Value": 4.83386,
                "ArriveTangent": 4.451988,
                "ArriveTangentWeight": 0.0,
                "LeaveTangent": 4.451988,
                "LeaveTangentWeight": 0.0
              },
              {
                "InterpMode": "RCIM_Linear",
                "TangentMode": "RCTM_Auto",
                "TangentWeightMode": "RCTWM_WeightedNone",
                "Time": 3.266667,
                "Value": 4.451988,
                "ArriveTangent": 4.451988,
                "ArriveTangentWeight": 0.0,
                "LeaveTangent": 0.0,
                "LeaveTangentWeight": 0.0
              },
              {
                "InterpMode": "RCIM_Linear",
                "TangentMode": "RCTM_Auto",
                "TangentWeightMode": "RCTWM_WeightedNone",
                "Time": 3.3000002,
                "Value": 4.451988,
                "ArriveTangent": 0.0,
                "ArriveTangentWeight": 0.0,
                "LeaveTangent": 0.35939232,
                "LeaveTangentWeight": 0.0
              }
            ],
            "DefaultValue": 3.4028235E+38,
            "PreInfinityExtrap": "RCCE_Constant",
            "PostInfinityExtrap": "RCCE_Constant"
          },
          "Name": {
            "DisplayName": "Speed"
          },
          "CurveTypeFlags": 4
        },
        {
          "FloatCurve": {
            "Keys": [
              {
                "InterpMode": "RCIM_Linear",
                "TangentMode": "RCTM_Auto",
                "TangentWeightMode": "RCTWM_WeightedNone",
                "Time": 0.0,
                "Value": 0.90000004,
                "ArriveTangent": 0.16666667,
                "ArriveTangentWeight": 0.0,
                "LeaveTangent": 0.13333334,
                "LeaveTangentWeight": 0.0
              },
              {
                "InterpMode": "RCIM_Linear",
                "TangentMode": "RCTM_Auto",
                "TangentWeightMode": "RCTWM_WeightedNone",
                "Time": 0.35939232,
                "Value": 0.16666667,
                "ArriveTangent": 0.13333334,
                "ArriveTangentWeight": 0.0,
                "LeaveTangent": 0.10000001,
                "LeaveTangentWeight": 0.0
              },
              {
                "InterpMode": "RCIM_Linear",
                "TangentMode": "RCTM_Auto",
                "TangentWeightMode": "RCTWM_WeightedNone",
                "Time": 0.51985794,
                "Value": 0.13333334,
                "ArriveTangent": 0.10000001,
                "ArriveTangentWeight": 0.0,
                "LeaveTangent": 0.06666667,
                "LeaveTangentWeight": 0.0
              },
              {
                "InterpMode": "RCIM_Linear",
                "TangentMode": "RCTM_Auto",
                "TangentWeightMode": "RCTWM_WeightedNone",
                "Time": 0.7125176,
                "Value": 0.10000001,
                "ArriveTangent": 0.06666667,
                "ArriveTangentWeight": 0.0,
                "LeaveTangent": 0.033333335,
                "LeaveTangentWeight": 0.0
              },
              {
                "InterpMode": "RCIM_Linear",
                "TangentMode": "RCTM_Auto",
                "TangentWeightMode": "RCTWM_WeightedNone",
                "Time": 0.947622,
                "Value": 0.06666667,
                "ArriveTangent": 0.033333335,
                "ArriveTangentWeight": 0.0,
                "LeaveTangent": 0.0,
                "LeaveTangentWeight": 0.0
              },
              {
                "InterpMode": "RCIM_Linear",
                "TangentMode": "RCTM_Auto",
                "TangentWeightMode": "RCTWM_WeightedNone",
                "Time": 1.4565175,
                "Value": 0.033333335,
                "ArriveTangent": 0.0,
                "ArriveTangentWeight": 0.0,
                "LeaveTangent": 0.36666667,
                "LeaveTangentWeight": 0.0
              },
              {
                "InterpMode": "RCIM_Linear",
                "TangentMode": "RCTM_Auto",
                "TangentWeightMode": "RCTWM_WeightedNone",
                "Time": 1.9314293,
                "Value": 0.0,
                "ArriveTangent": 0.36666667,
                "ArriveTangentWeight": 0.0,
                "LeaveTangent": 0.40000004,
                "LeaveTangentWeight": 0.0
              },
              {
                "InterpMode": "RCIM_Linear",
                "TangentMode": "RCTM_Auto",
                "TangentWeightMode": "RCTWM_WeightedNone",
                "Time": 2.1296287,
                "Value": 0.36666667,
                "ArriveTangent": 0.40000004,
                "ArriveTangentWeight": 0.0,
                "LeaveTangent": 0.43333337,
                "LeaveTangentWeight": 0.0
              },
              {
                "InterpMode": "RCIM_Linear",
                "TangentMode": "RCTM_Auto",
                "TangentWeightMode": "RCTWM_WeightedNone",
                "Time": 2.4543674,
                "Value": 0.40000004,
                "ArriveTangent": 0.43333337,
                "ArriveTangentWeight": 0.0,
                "LeaveTangent": 0.4666667,
                "LeaveTangentWeight": 0.0
              },
              {
                "InterpMode": "RCIM_Linear",
                "TangentMode": "RCTM_Auto",
                "TangentWeightMode": "RCTWM_WeightedNone",
                "Time": 2.5124524,
                "Value": 0.43333337,
                "ArriveTangent": 0.4666667,
                "ArriveTangentWeight": 0.0,
                "LeaveTangent": 0.5,
                "LeaveTangentWeight": 0.0
              },
              {
                "InterpMode": "RCIM_Linear",
                "TangentMode": "RCTM_Auto",
                "TangentWeightMode": "RCTWM_WeightedNone",
                "Time": 2.689678,
                "Value": 0.4666667,
                "ArriveTangent": 0.5,
                "ArriveTangentWeight": 0.0,
                "LeaveTangent": 0.53333336,
                "LeaveTangentWeight": 0.0
              },
              {
                "InterpMode": "RCIM_Linear",
                "TangentMode": "RCTM_Auto",
                "TangentWeightMode": "RCTWM_WeightedNone",
                "Time": 3.2333827,
                "Value": 0.5,
                "ArriveTangent": 0.53333336,
                "ArriveTangentWeight": 0.0,
                "LeaveTangent": 0.0,
                "LeaveTangentWeight": 0.0
              },
              {
                "InterpMode": "RCIM_Linear",
                "TangentMode": "RCTM_Auto",
                "TangentWeightMode": "RCTWM_WeightedNone",
                "Time": 3.3000002,
                "Value": 0.53333336,
                "ArriveTangent": 0.0,
                "ArriveTangentWeight": 0.0,
                "LeaveTangent": 0.0,
                "LeaveTangentWeight": 0.0
              }
            ],
            "DefaultValue": 3.4028235E+38,
            "PreInfinityExtrap": "RCCE_Constant",
            "PostInfinityExtrap": "RCCE_Constant"
          },
          "Name": {
            "DisplayName": "SpeedToTime"
          },
          "CurveTypeFlags": 4
        },
        {
          "FloatCurve": {
            "Keys": [
              {
                "InterpMode": "RCIM_Linear",
                "TangentMode": "RCTM_Auto",
                "TangentWeightMode": "RCTWM_WeightedNone",
                "Time": 0.0,
                "Value": 2.9653807,
                "ArriveTangent": 0.0,
                "ArriveTangentWeight": 0.0,
                "LeaveTangent": 0.0,
                "LeaveTangentWeight": 0.0
              }
            ],
            "DefaultValue": 3.4028235E+38,
            "PreInfinityExtrap": "RCCE_Constant",
            "PostInfinityExtrap": "RCCE_Constant"
          },
          "Name": {
            "DisplayName": "AverageSpeed"
          },
          "CurveTypeFlags": 4
        }
      ]
    },
    "CompressedDataStructure": {
      "CompressedNumberOfFrames": 100
    },
    "BoneCompressionCodec": {
      "ObjectName": "AnimBoneCompressionCodec_ACL'AC_PhxAnimBoneCompressionSettings_Cinematic:AnimBoneCompressionCodec_ACL_0'",
      "ObjectPath": "/Game/Animation/Settings/AC_PhxAnimBoneCompressionSettings_Cinematic"
    },
    "CurveCompressionCodec": {
      "ObjectName": "AnimCurveCompressionCodec_CompressedRichCurve'AC_PhxAnimCurveCompressionSettings:CurveCompressionCodec'",
      "ObjectPath": "/Game/Animation/Settings/AC_PhxAnimCurveCompressionSettings"
    },
    "CompressedRawDataSize": 281044
  }
]